[{"throttle": 0.75, "steer": 0.006096068769693375, "brake": 0.0, "hand_brake": false, "reverse": false, "manual_gear_shift": false, "gear": 0, "frame": 0}, {"throttle": 0.75, "steer": 0.006105097476392984, "brake": 0.0, "hand_brake": false, "reverse": false, "manual_gear_shift": false, "gear": 0, "frame": 1}, {"throttle": 0.75, "steer": 0.006114108953624964, "brake": 0.0, "hand_brake": false, "reverse": false, "manual_gear_shift": false, "gear": 0, "frame": 2}, {"throttle": 0.75, "steer": 0.006129666697233915, "brake": 0.0, "hand_brake": false, "reverse": false, "manual_gear_shift": false, "gear": 0, "frame": 3}, {"throttle": 0.75, "steer": 0.006138661410659552, "brake": 0.0, "hand_brake": false, "reverse": false, "manual_gear_shift": false, "gear": 0, "frame": 4}, {"throttle": 0.75, "steer": 0.006125486455857754, "brake": 0.0, "hand_brake": false, "reverse": false, "manual_gear_shift": false, "gear": 0, "frame": 5}, {"throttle": 0.75, "steer": 0.006125418934971094, "brake": 0.0, "hand_brake": false, "reverse": false, "manual_gear_shift": false, "gear": 0, "frame": 6}, {"throttle": 0.75, "steer": 0.006127537693828344, "brake": 0.0, "hand_brake": false, "reverse": false, "manual_gear_shift": false, "gear": 0, "frame": 7}, {"throttle": 0.75, "steer": 0.005746146664023399, "brake": 0.0, "hand_brake": false, "reverse": false, "manual_gear_shift": false, "gear": 0, "frame": 8}, {"throttle": 0.75, "steer": 0.002897243946790695, "brake": 0.0, "hand_brake": false, "reverse": false, "manual_gear_shift": false, "gear": 0, "frame": 9}, {"throttle": 0.75, "steer": -0.0008419905789196491, "brake": 0.0, "hand_brake": false, "reverse": false, "manual_gear_shift": false, "gear": 0, "frame": 10}, {"throttle": 0.75, "steer": 0.00025642276159487665, "brake": 0.0, "hand_brake": false, "reverse": false, "manual_gear_shift": false, "gear": 0, "frame": 11}, {"throttle": 0.75, "steer": 0.0032824333757162094, "brake": 0.0, "hand_brake": false, "reverse": false, "manual_gear_shift": false, "gear": 0, "frame": 12}, {"throttle": 0.75, "steer": 0.010395576246082783, "brake": 0.0, "hand_brake": false, "reverse": false, "manual_gear_shift": false, "gear": 0, "frame": 13}, {"throttle": 0.75, "steer": 0.017450906336307526, "brake": 0.0, "hand_brake": false, "reverse": false, "manual_gear_shift": false, "gear": 0, "frame": 14}, {"throttle": 0.75, "steer": 0.06280480325222015, "brake": 0.0, "hand_brake": false, "reverse": false, "manual_gear_shift": false, "gear": 0, "frame": 15}, {"throttle": 0.75, "steer": 0.060683175921440125, "brake": 0.0, "hand_brake": false, "reverse": false, "manual_gear_shift": false, "gear": 0, "frame": 16}, {"throttle": 0.75, "steer": 0.062325652688741684, "brake": 0.0, "hand_brake": false, "reverse": false, "manual_gear_shift": false, "gear": 0, "frame": 17}, {"throttle": 0.75, "steer": 0.06199533864855766, "brake": 0.0, "hand_brake": false, "reverse": false, "manual_gear_shift": false, "gear": 0, "frame": 18}, {"throttle": 0.75, "steer": 0.05435633659362793, "brake": 0.0, "hand_brake": false, "reverse": false, "manual_gear_shift": false, "gear": 0, "frame": 19}, {"throttle": 0.75, "steer": 0.04535963758826256, "brake": 0.0, "hand_brake": false, "reverse": false, "manual_gear_shift": false, "gear": 0, "frame": 20}, {"throttle": 0.75, "steer": 0.04744638875126839, "brake": 0.0, "hand_brake": false, "reverse": false, "manual_gear_shift": false, "gear": 0, "frame": 21}, {"throttle": 0.75, "steer": 0.18841521441936493, "brake": 0.0, "hand_brake": false, "reverse": false, "manual_gear_shift": false, "gear": 0, "frame": 22}, {"throttle": 0.75, "steer": 0.18233177065849304, "brake": 0.0, "hand_brake": false, "reverse": false, "manual_gear_shift": false, "gear": 0, "frame": 23}, {"throttle": 0.75, "steer": 0.16646304726600647, "brake": 0.0, "hand_brake": false, "reverse": false, "manual_gear_shift": false, "gear": 0, "frame": 24}, {"throttle": 0.75, "steer": 0.1379227191209793, "brake": 0.0, "hand_brake": false, "reverse": false, "manual_gear_shift": false, "gear": 0, "frame": 25}, {"throttle": 0.75, "steer": 0.09960473328828812, "brake": 0.0, "hand_brake": false, "reverse": false, "manual_gear_shift": false, "gear": 0, "frame": 26}, {"throttle": 0.75, "steer": 0.2715001106262207, "brake": 0.0, "hand_brake": false, "reverse": false, "manual_gear_shift": false, "gear": 0, "frame": 27}, {"throttle": 0.75, "steer": 0.23384399712085724, "brake": 0.0, "hand_brake": false, "reverse": false, "manual_gear_shift": false, "gear": 0, "frame": 28}, {"throttle": 0.75, "steer": 0.19258368015289307, "brake": 0.0, "hand_brake": false, "reverse": false, "manual_gear_shift": false, "gear": 0, "frame": 29}, {"throttle": 0.75, "steer": 0.19830314815044403, "brake": 0.0, "hand_brake": false, "reverse": false, "manual_gear_shift": false, "gear": 0, "frame": 30}, {"throttle": 0.75, "steer": 0.29830315709114075, "brake": 0.0, "hand_brake": false, "reverse": false, "manual_gear_shift": false, "gear": 0, "frame": 31}, {"throttle": 0.75, "steer": 0.39830315113067627, "brake": 0.0, "hand_brake": false, "reverse": false, "manual_gear_shift": false, "gear": 0, "frame": 32}, {"throttle": 0.75, "steer": 0.3830021023750305, "brake": 0.0, "hand_brake": false, "reverse": false, "manual_gear_shift": false, "gear": 0, "frame": 33}, {"throttle": 0.75, "steer": 0.3001488149166107, "brake": 0.0, "hand_brake": false, "reverse": false, "manual_gear_shift": false, "gear": 0, "frame": 34}, {"throttle": 0.75, "steer": 0.2445477396249771, "brake": 0.0, "hand_brake": false, "reverse": false, "manual_gear_shift": false, "gear": 0, "frame": 35}, {"throttle": 0.75, "steer": 0.34454774856567383, "brake": 0.0, "hand_brake": false, "reverse": false, "manual_gear_shift": false, "gear": 0, "frame": 36}, {"throttle": 0.75, "steer": 0.44225192070007324, "brake": 0.0, "hand_brake": false, "reverse": false, "manual_gear_shift": false, "gear": 0, "frame": 37}, {"throttle": 0.75, "steer": 0.3450108468532562, "brake": 0.0, "hand_brake": false, "reverse": false, "manual_gear_shift": false, "gear": 0, "frame": 38}, {"throttle": 0.75, "steer": 0.2527781128883362, "brake": 0.0, "hand_brake": false, "reverse": false, "manual_gear_shift": false, "gear": 0, "frame": 39}, {"throttle": 0.75, "steer": 0.3527781069278717, "brake": 0.0, "hand_brake": false, "reverse": false, "manual_gear_shift": false, "gear": 0, "frame": 40}, {"throttle": 0.75, "steer": 0.4527781009674072, "brake": 0.0, "hand_brake": false, "reverse": false, "manual_gear_shift": false, "gear": 0, "frame": 41}, {"throttle": 0.7169936895370483, "steer": 0.5527781248092651, "brake": 0.0, "hand_brake": false, "reverse": false, "manual_gear_shift": false, "gear": 0, "frame": 42}, {"throttle": 0.6450318098068237, "steer": 0.6527780890464783, "brake": 0.0, "hand_brake": false, "reverse": false, "manual_gear_shift": false, "gear": 0, "frame": 43}, {"throttle": 0.6026661992073059, "steer": 0.7527781128883362, "brake": 0.0, "hand_brake": false, "reverse": false, "manual_gear_shift": false, "gear": 0, "frame": 44}, {"throttle": 0.569543719291687, "steer": 0.6563934683799744, "brake": 0.0, "hand_brake": false, "reverse": false, "manual_gear_shift": false, "gear": 0, "frame": 45}, {"throttle": 0.6179596781730652, "steer": 0.5563934445381165, "brake": 0.0, "hand_brake": false, "reverse": false, "manual_gear_shift": false, "gear": 0, "frame": 46}, {"throttle": 0.5225273966789246, "steer": 0.4563934803009033, "brake": 0.0, "hand_brake": false, "reverse": false, "manual_gear_shift": false, "gear": 0, "frame": 47}, {"throttle": 0.45208054780960083, "steer": 0.5563934445381165, "brake": 0.0, "hand_brake": false, "reverse": false, "manual_gear_shift": false, "gear": 0, "frame": 48}, {"throttle": 0.43822264671325684, "steer": 0.5363191962242126, "brake": 0.0, "hand_brake": false, "reverse": false, "manual_gear_shift": false, "gear": 0, "frame": 49}, {"throttle": 0.4524514675140381, "steer": 0.4363192021846771, "brake": 0.0, "hand_brake": false, "reverse": false, "manual_gear_shift": false, "gear": 0, "frame": 50}, {"throttle": 0.3732971251010895, "steer": 0.3363192081451416, "brake": 0.0, "hand_brake": false, "reverse": false, "manual_gear_shift": false, "gear": 0, "frame": 51}, {"throttle": 0.2898290753364563, "steer": 0.4363192021846771, "brake": 0.0, "hand_brake": false, "reverse": false, "manual_gear_shift": false, "gear": 0, "frame": 52}, {"throttle": 0.2819296717643738, "steer": 0.4820220172405243, "brake": 0.0, "hand_brake": false, "reverse": false, "manual_gear_shift": false, "gear": 0, "frame": 53}, {"throttle": 0.32632333040237427, "steer": 0.40490952134132385, "brake": 0.0, "hand_brake": false, "reverse": false, "manual_gear_shift": false, "gear": 0, "frame": 54}, {"throttle": 0.3753511309623718, "steer": 0.30490952730178833, "brake": 0.0, "hand_brake": false, "reverse": false, "manual_gear_shift": false, "gear": 0, "frame": 55}, {"throttle": 0.3390432894229889, "steer": 0.21065634489059448, "brake": 0.0, "hand_brake": false, "reverse": false, "manual_gear_shift": false, "gear": 0, "frame": 56}, {"throttle": 0.3498135507106781, "steer": 0.31065633893013, "brake": 0.0, "hand_brake": false, "reverse": false, "manual_gear_shift": false, "gear": 0, "frame": 57}, {"throttle": 0.33606866002082825, "steer": 0.23423165082931519, "brake": 0.0, "hand_brake": false, "reverse": false, "manual_gear_shift": false, "gear": 0, "frame": 58}, {"throttle": 0.3374827802181244, "steer": 0.18198004364967346, "brake": 0.0, "hand_brake": false, "reverse": false, "manual_gear_shift": false, "gear": 0, "frame": 59}, {"throttle": 0.34043699502944946, "steer": 0.16458144783973694, "brake": 0.0, "hand_brake": false, "reverse": false, "manual_gear_shift": false, "gear": 0, "frame": 60}, {"throttle": 0.37907087802886963, "steer": 0.12772199511528015, "brake": 0.0, "hand_brake": false, "reverse": false, "manual_gear_shift": false, "gear": 0, "frame": 61}, {"throttle": 0.39062637090682983, "steer": 0.1263425499200821, "brake": 0.0, "hand_brake": false, "reverse": false, "manual_gear_shift": false, "gear": 0, "frame": 62}, {"throttle": 0.42003750801086426, "steer": 0.2263425588607788, "brake": 0.0, "hand_brake": false, "reverse": false, "manual_gear_shift": false, "gear": 0, "frame": 63}, {"throttle": 0.4368453323841095, "steer": 0.2969946265220642, "brake": 0.0, "hand_brake": false, "reverse": false, "manual_gear_shift": false, "gear": 0, "frame": 64}, {"throttle": 0.4768707752227783, "steer": 0.22940893471240997, "brake": 0.0, "hand_brake": false, "reverse": false, "manual_gear_shift": false, "gear": 0, "frame": 65}, {"throttle": 0.46501410007476807, "steer": 0.18225707113742828, "brake": 0.0, "hand_brake": false, "reverse": false, "manual_gear_shift": false, "gear": 0, "frame": 66}, {"throttle": 0.4617457985877991, "steer": 0.1560332179069519, "brake": 0.0, "hand_brake": false, "reverse": false, "manual_gear_shift": false, "gear": 0, "frame": 67}, {"throttle": 0.47690367698669434, "steer": 0.080940380692482, "brake": 0.0, "hand_brake": false, "reverse": false, "manual_gear_shift": false, "gear": 0, "frame": 68}, {"throttle": 0.4461177587509155, "steer": 0.1809403896331787, "brake": 0.0, "hand_brake": false, "reverse": false, "manual_gear_shift": false, "gear": 0, "frame": 69}, {"throttle": 0.4366840124130249, "steer": 0.0990624725818634, "brake": 0.0, "hand_brake": false, "reverse": false, "manual_gear_shift": false, "gear": 0, "frame": 70}, {"throttle": 0.4321626126766205, "steer": 0.043502822518348694, "brake": 0.0, "hand_brake": false, "reverse": false, "manual_gear_shift": false, "gear": 0, "frame": 71}, {"throttle": 0.4155854880809784, "steer": 0.03653506189584732, "brake": 0.0, "hand_brake": false, "reverse": false, "manual_gear_shift": false, "gear": 0, "frame": 72}, {"throttle": 0.4195311963558197, "steer": 0.08143298327922821, "brake": 0.0, "hand_brake": false, "reverse": false, "manual_gear_shift": false, "gear": 0, "frame": 73}, {"throttle": 0.4035036563873291, "steer": 0.10213702917098999, "brake": 0.0, "hand_brake": false, "reverse": false, "manual_gear_shift": false, "gear": 0, "frame": 74}, {"throttle": 0.3963622450828552, "steer": 0.2021370232105255, "brake": 0.0, "hand_brake": false, "reverse": false, "manual_gear_shift": false, "gear": 0, "frame": 75}, {"throttle": 0.38965725898742676, "steer": 0.10213702917098999, "brake": 0.0, "hand_brake": false, "reverse": false, "manual_gear_shift": false, "gear": 0, "frame": 76}, {"throttle": 0.38508090376853943, "steer": 0.06577413529157639, "brake": 0.0, "hand_brake": false, "reverse": false, "manual_gear_shift": false, "gear": 0, "frame": 77}, {"throttle": 0.3823092579841614, "steer": 0.09514224529266357, "brake": 0.0, "hand_brake": false, "reverse": false, "manual_gear_shift": false, "gear": 0, "frame": 78}, {"throttle": 0.39798417687416077, "steer": 0.060358885675668716, "brake": 0.0, "hand_brake": false, "reverse": false, "manual_gear_shift": false, "gear": 0, "frame": 79}, {"throttle": 0.4038931429386139, "steer": 0.12132007628679276, "brake": 0.0, "hand_brake": false, "reverse": false, "manual_gear_shift": false, "gear": 0, "frame": 80}, {"throttle": 0.4071058928966522, "steer": 0.0418851301074028, "brake": 0.0, "hand_brake": false, "reverse": false, "manual_gear_shift": false, "gear": 0, "frame": 81}, {"throttle": 0.41937747597694397, "steer": 0.07598662376403809, "brake": 0.0, "hand_brake": false, "reverse": false, "manual_gear_shift": false, "gear": 0, "frame": 82}, {"throttle": 0.4310128390789032, "steer": 0.11657863855361938, "brake": 0.0, "hand_brake": false, "reverse": false, "manual_gear_shift": false, "gear": 0, "frame": 83}, {"throttle": 0.4238753914833069, "steer": 0.12421432882547379, "brake": 0.0, "hand_brake": false, "reverse": false, "manual_gear_shift": false, "gear": 0, "frame": 84}, {"throttle": 0.45345643162727356, "steer": 0.048505011945962906, "brake": 0.0, "hand_brake": false, "reverse": false, "manual_gear_shift": false, "gear": 0, "frame": 85}, {"throttle": 0.4466981589794159, "steer": 0.055361442267894745, "brake": 0.0, "hand_brake": false, "reverse": false, "manual_gear_shift": false, "gear": 0, "frame": 86}, {"throttle": 0.45268893241882324, "steer": -0.044638559222221375, "brake": 0.0, "hand_brake": false, "reverse": false, "manual_gear_shift": false, "gear": 0, "frame": 87}, {"throttle": 0.43194887042045593, "steer": -0.07320760935544968, "brake": 0.0, "hand_brake": false, "reverse": false, "manual_gear_shift": false, "gear": 0, "frame": 88}, {"throttle": 0.43673062324523926, "steer": -0.03299398347735405, "brake": 0.0, "hand_brake": false, "reverse": false, "manual_gear_shift": false, "gear": 0, "frame": 89}, {"throttle": 0.43894070386886597, "steer": 0.0018857045797631145, "brake": 0.0, "hand_brake": false, "reverse": false, "manual_gear_shift": false, "gear": 0, "frame": 90}, {"throttle": 0.44173356890678406, "steer": -0.013228814117610455, "brake": 0.0, "hand_brake": false, "reverse": false, "manual_gear_shift": false, "gear": 0, "frame": 91}, {"throttle": 0.4457749128341675, "steer": 0.024146491661667824, "brake": 0.0, "hand_brake": false, "reverse": false, "manual_gear_shift": false, "gear": 0, "frame": 92}, {"throttle": 0.44092684984207153, "steer": -0.04614638537168503, "brake": 0.0, "hand_brake": false, "reverse": false, "manual_gear_shift": false, "gear": 0, "frame": 93}, {"throttle": 0.4391780495643616, "steer": -0.025491910055279732, "brake": 0.0, "hand_brake": false, "reverse": false, "manual_gear_shift": false, "gear": 0, "frame": 94}, {"throttle": 0.43567875027656555, "steer": -0.016759755089879036, "brake": 0.0, "hand_brake": false, "reverse": false, "manual_gear_shift": false, "gear": 0, "frame": 95}, {"throttle": 0.4301450848579407, "steer": -0.012895137071609497, "brake": 0.0, "hand_brake": false, "reverse": false, "manual_gear_shift": false, "gear": 0, "frame": 96}, {"throttle": 0.410629540681839, "steer": -0.005281426012516022, "brake": 0.0, "hand_brake": false, "reverse": false, "manual_gear_shift": false, "gear": 0, "frame": 97}, {"throttle": 0.38811543583869934, "steer": 0.04999078810214996, "brake": 0.0, "hand_brake": false, "reverse": false, "manual_gear_shift": false, "gear": 0, "frame": 98}, {"throttle": 0.3867296278476715, "steer": 0.046414583921432495, "brake": 0.0, "hand_brake": false, "reverse": false, "manual_gear_shift": false, "gear": 0, "frame": 99}, {"throttle": 0.37694215774536133, "steer": 0.06939631700515747, "brake": 0.0, "hand_brake": false, "reverse": false, "manual_gear_shift": false, "gear": 0, "frame": 100}, {"throttle": 0.36406654119491577, "steer": 0.03929673880338669, "brake": 0.0, "hand_brake": false, "reverse": false, "manual_gear_shift": false, "gear": 0, "frame": 101}, {"throttle": 0.3653833568096161, "steer": 0.0158657506108284, "brake": 0.0, "hand_brake": false, "reverse": false, "manual_gear_shift": false, "gear": 0, "frame": 102}, {"throttle": 0.365126371383667, "steer": 0.0009468491189181805, "brake": 0.0, "hand_brake": false, "reverse": false, "manual_gear_shift": false, "gear": 0, "frame": 103}, {"throttle": 0.3663930594921112, "steer": -0.03246483951807022, "brake": 0.0, "hand_brake": false, "reverse": false, "manual_gear_shift": false, "gear": 0, "frame": 104}, {"throttle": 0.3767305016517639, "steer": -0.014731314964592457, "brake": 0.0, "hand_brake": false, "reverse": false, "manual_gear_shift": false, "gear": 0, "frame": 105}, {"throttle": 0.37744271755218506, "steer": 0.0015960901509970427, "brake": 0.0, "hand_brake": false, "reverse": false, "manual_gear_shift": false, "gear": 0, "frame": 106}, {"throttle": 0.3802180886268616, "steer": 0.00042107803164981306, "brake": 0.0, "hand_brake": false, "reverse": false, "manual_gear_shift": false, "gear": 0, "frame": 107}, {"throttle": 0.4000307023525238, "steer": 0.04716547578573227, "brake": 0.0, "hand_brake": false, "reverse": false, "manual_gear_shift": false, "gear": 0, "frame": 108}, {"throttle": 0.4186924397945404, "steer": 0.07462966442108154, "brake": 0.0, "hand_brake": false, "reverse": false, "manual_gear_shift": false, "gear": 0, "frame": 109}, {"throttle": 0.43014127016067505, "steer": 0.027387304231524467, "brake": 0.0, "hand_brake": false, "reverse": false, "manual_gear_shift": false, "gear": 0, "frame": 110}, {"throttle": 0.4181537926197052, "steer": 0.017009230330586433, "brake": 0.0, "hand_brake": false, "reverse": false, "manual_gear_shift": false, "gear": 0, "frame": 111}, {"throttle": 0.3977682590484619, "steer": 0.035876449197530746, "brake": 0.0, "hand_brake": false, "reverse": false, "manual_gear_shift": false, "gear": 0, "frame": 112}, {"throttle": 0.39524632692337036, "steer": 0.012305265292525291, "brake": 0.0, "hand_brake": false, "reverse": false, "manual_gear_shift": false, "gear": 0, "frame": 113}, {"throttle": 0.3753911554813385, "steer": -0.022049251943826675, "brake": 0.0, "hand_brake": false, "reverse": false, "manual_gear_shift": false, "gear": 0, "frame": 114}, {"throttle": 0.36748334765434265, "steer": 0.004580793436616659, "brake": 0.0, "hand_brake": false, "reverse": false, "manual_gear_shift": false, "gear": 0, "frame": 115}, {"throttle": 0.3557138442993164, "steer": 0.008846797980368137, "brake": 0.0, "hand_brake": false, "reverse": false, "manual_gear_shift": false, "gear": 0, "frame": 116}, {"throttle": 0.35957399010658264, "steer": -0.01814977638423443, "brake": 0.0, "hand_brake": false, "reverse": false, "manual_gear_shift": false, "gear": 0, "frame": 117}, {"throttle": 0.3760046660900116, "steer": -0.006023980677127838, "brake": 0.0, "hand_brake": false, "reverse": false, "manual_gear_shift": false, "gear": 0, "frame": 118}, {"throttle": 0.4153721332550049, "steer": 0.04456685855984688, "brake": 0.0, "hand_brake": false, "reverse": false, "manual_gear_shift": false, "gear": 0, "frame": 119}, {"throttle": 0.4341343343257904, "steer": 0.12369360774755478, "brake": 0.0, "hand_brake": false, "reverse": false, "manual_gear_shift": false, "gear": 0, "frame": 120}, {"throttle": 0.4447821378707886, "steer": 0.13827717304229736, "brake": 0.0, "hand_brake": false, "reverse": false, "manual_gear_shift": false, "gear": 0, "frame": 121}, {"throttle": 0.47172755002975464, "steer": 0.0766216441988945, "brake": 0.0, "hand_brake": false, "reverse": false, "manual_gear_shift": false, "gear": 0, "frame": 122}, {"throttle": 0.47882381081581116, "steer": 0.011144271120429039, "brake": 0.0, "hand_brake": false, "reverse": false, "manual_gear_shift": false, "gear": 0, "frame": 123}, {"throttle": 0.4732295274734497, "steer": -0.03660408779978752, "brake": 0.0, "hand_brake": false, "reverse": false, "manual_gear_shift": false, "gear": 0, "frame": 124}, {"throttle": 0.4752628803253174, "steer": -0.04372572898864746, "brake": 0.0, "hand_brake": false, "reverse": false, "manual_gear_shift": false, "gear": 0, "frame": 125}, {"throttle": 0.481533408164978, "steer": 0.02260754071176052, "brake": 0.0, "hand_brake": false, "reverse": false, "manual_gear_shift": false, "gear": 0, "frame": 126}, {"throttle": 0.46874701976776123, "steer": 0.02581416442990303, "brake": 0.0, "hand_brake": false, "reverse": false, "manual_gear_shift": false, "gear": 0, "frame": 127}, {"throttle": 0.44108033180236816, "steer": 0.01839463971555233, "brake": 0.0, "hand_brake": false, "reverse": false, "manual_gear_shift": false, "gear": 0, "frame": 128}, {"throttle": 0.4049140512943268, "steer": 0.016219237819314003, "brake": 0.0, "hand_brake": false, "reverse": false, "manual_gear_shift": false, "gear": 0, "frame": 129}, {"throttle": 0.3827085494995117, "steer": 0.04489274322986603, "brake": 0.0, "hand_brake": false, "reverse": false, "manual_gear_shift": false, "gear": 0, "frame": 130}, {"throttle": 0.36029601097106934, "steer": 0.05098065361380577, "brake": 0.0, "hand_brake": false, "reverse": false, "manual_gear_shift": false, "gear": 0, "frame": 131}, {"throttle": 0.35389405488967896, "steer": 0.005587644409388304, "brake": 0.0, "hand_brake": false, "reverse": false, "manual_gear_shift": false, "gear": 0, "frame": 132}, {"throttle": 0.3505800664424896, "steer": -0.03778868541121483, "brake": 0.0, "hand_brake": false, "reverse": false, "manual_gear_shift": false, "gear": 0, "frame": 133}, {"throttle": 0.34728315472602844, "steer": -0.07377304881811142, "brake": 0.0, "hand_brake": false, "reverse": false, "manual_gear_shift": false, "gear": 0, "frame": 134}, {"throttle": 0.3560706079006195, "steer": -0.07433512806892395, "brake": 0.0, "hand_brake": false, "reverse": false, "manual_gear_shift": false, "gear": 0, "frame": 135}, {"throttle": 0.36428582668304443, "steer": -0.02714717388153076, "brake": 0.0, "hand_brake": false, "reverse": false, "manual_gear_shift": false, "gear": 0, "frame": 136}, {"throttle": 0.3705831468105316, "steer": -0.008256237022578716, "brake": 0.0, "hand_brake": false, "reverse": false, "manual_gear_shift": false, "gear": 0, "frame": 137}, {"throttle": 0.37381643056869507, "steer": -0.01645059883594513, "brake": 0.0, "hand_brake": false, "reverse": false, "manual_gear_shift": false, "gear": 0, "frame": 138}, {"throttle": 0.3754926323890686, "steer": -0.02473808452486992, "brake": 0.0, "hand_brake": false, "reverse": false, "manual_gear_shift": false, "gear": 0, "frame": 139}, {"throttle": 0.37959790229797363, "steer": -0.008839495480060577, "brake": 0.0, "hand_brake": false, "reverse": false, "manual_gear_shift": false, "gear": 0, "frame": 140}, {"throttle": 0.38827234506607056, "steer": -0.04457549378275871, "brake": 0.0, "hand_brake": false, "reverse": false, "manual_gear_shift": false, "gear": 0, "frame": 141}, {"throttle": 0.40104883909225464, "steer": -0.026782071217894554, "brake": 0.0, "hand_brake": false, "reverse": false, "manual_gear_shift": false, "gear": 0, "frame": 142}, {"throttle": 0.4028046429157257, "steer": -0.016194263473153114, "brake": 0.0, "hand_brake": false, "reverse": false, "manual_gear_shift": false, "gear": 0, "frame": 143}, {"throttle": 0.4112812876701355, "steer": -3.654855754575692e-05, "brake": 0.0, "hand_brake": false, "reverse": false, "manual_gear_shift": false, "gear": 0, "frame": 144}, {"throttle": 0.4160001277923584, "steer": 0.011579013429582119, "brake": 0.0, "hand_brake": false, "reverse": false, "manual_gear_shift": false, "gear": 0, "frame": 145}, {"throttle": 0.4128560721874237, "steer": 0.006422332488000393, "brake": 0.0, "hand_brake": false, "reverse": false, "manual_gear_shift": false, "gear": 0, "frame": 146}, {"throttle": 0.42500874400138855, "steer": 0.028919585049152374, "brake": 0.0, "hand_brake": false, "reverse": false, "manual_gear_shift": false, "gear": 0, "frame": 147}, {"throttle": 0.4420166015625, "steer": 0.05021638050675392, "brake": 0.0, "hand_brake": false, "reverse": false, "manual_gear_shift": false, "gear": 0, "frame": 148}, {"throttle": 0.451315701007843, "steer": 0.03868674859404564, "brake": 0.0, "hand_brake": false, "reverse": false, "manual_gear_shift": false, "gear": 0, "frame": 149}, {"throttle": 0.4801834225654602, "steer": 0.11071163415908813, "brake": 0.0, "hand_brake": false, "reverse": false, "manual_gear_shift": false, "gear": 0, "frame": 150}, {"throttle": 0.0727001428604126, "steer": 0.08553525805473328, "brake": 0.0, "hand_brake": false, "reverse": false, "manual_gear_shift": false, "gear": 0, "frame": 151}, {"throttle": 0.08612585812807083, "steer": 0.09358947724103928, "brake": 0.0, "hand_brake": false, "reverse": false, "manual_gear_shift": false, "gear": 0, "frame": 152}, {"throttle": 0.09877438098192215, "steer": 0.08223206549882889, "brake": 0.0, "hand_brake": false, "reverse": false, "manual_gear_shift": false, "gear": 0, "frame": 153}, {"throttle": 0.1288854032754898, "steer": 0.06607718765735626, "brake": 0.0, "hand_brake": false, "reverse": false, "manual_gear_shift": false, "gear": 0, "frame": 154}, {"throttle": 0.16231416165828705, "steer": 0.053266916424036026, "brake": 0.0, "hand_brake": false, "reverse": false, "manual_gear_shift": false, "gear": 0, "frame": 155}, {"throttle": 0.20475807785987854, "steer": 0.037972256541252136, "brake": 0.0, "hand_brake": false, "reverse": false, "manual_gear_shift": false, "gear": 0, "frame": 156}, {"throttle": 0.25383976101875305, "steer": 0.030455665662884712, "brake": 0.0, "hand_brake": false, "reverse": false, "manual_gear_shift": false, "gear": 0, "frame": 157}, {"throttle": 0.29673317074775696, "steer": 0.03389759361743927, "brake": 0.0, "hand_brake": false, "reverse": false, "manual_gear_shift": false, "gear": 0, "frame": 158}, {"throttle": 0.33369138836860657, "steer": 0.03058556467294693, "brake": 0.0, "hand_brake": false, "reverse": false, "manual_gear_shift": false, "gear": 0, "frame": 159}, {"throttle": 0.3730558454990387, "steer": 0.0340794175863266, "brake": 0.0, "hand_brake": false, "reverse": false, "manual_gear_shift": false, "gear": 0, "frame": 160}, {"throttle": 0.4119184911251068, "steer": 0.03561824932694435, "brake": 0.0, "hand_brake": false, "reverse": false, "manual_gear_shift": false, "gear": 0, "frame": 161}, {"throttle": 0.44138920307159424, "steer": 0.034150924533605576, "brake": 0.0, "hand_brake": false, "reverse": false, "manual_gear_shift": false, "gear": 0, "frame": 162}, {"throttle": 0.4706879258155823, "steer": 0.047897934913635254, "brake": 0.0, "hand_brake": false, "reverse": false, "manual_gear_shift": false, "gear": 0, "frame": 163}, {"throttle": 0.4731456935405731, "steer": 0.06605029106140137, "brake": 0.0, "hand_brake": false, "reverse": false, "manual_gear_shift": false, "gear": 0, "frame": 164}, {"throttle": 0.47120553255081177, "steer": 0.07268500328063965, "brake": 0.0, "hand_brake": false, "reverse": false, "manual_gear_shift": false, "gear": 0, "frame": 165}, {"throttle": 0.4666348099708557, "steer": 0.08363822102546692, "brake": 0.0, "hand_brake": false, "reverse": false, "manual_gear_shift": false, "gear": 0, "frame": 166}, {"throttle": 0.4608832001686096, "steer": 0.08677032589912415, "brake": 0.0, "hand_brake": false, "reverse": false, "manual_gear_shift": false, "gear": 0, "frame": 167}, {"throttle": 0.4363020062446594, "steer": 0.08495787531137466, "brake": 0.0, "hand_brake": false, "reverse": false, "manual_gear_shift": false, "gear": 0, "frame": 168}, {"throttle": 0.39575615525245667, "steer": 0.08399015665054321, "brake": 0.0, "hand_brake": false, "reverse": false, "manual_gear_shift": false, "gear": 0, "frame": 169}, {"throttle": 0.35415035486221313, "steer": 0.08150304108858109, "brake": 0.0, "hand_brake": false, "reverse": false, "manual_gear_shift": false, "gear": 0, "frame": 170}, {"throttle": 0.3235059380531311, "steer": 0.06867877393960953, "brake": 0.0, "hand_brake": false, "reverse": false, "manual_gear_shift": false, "gear": 0, "frame": 171}, {"throttle": 0.30104514956474304, "steer": 0.04374341666698456, "brake": 0.0, "hand_brake": false, "reverse": false, "manual_gear_shift": false, "gear": 0, "frame": 172}, {"throttle": 0.29441630840301514, "steer": 0.040782034397125244, "brake": 0.0, "hand_brake": false, "reverse": false, "manual_gear_shift": false, "gear": 0, "frame": 173}, {"throttle": 0.2819581925868988, "steer": 0.049627095460891724, "brake": 0.0, "hand_brake": false, "reverse": false, "manual_gear_shift": false, "gear": 0, "frame": 174}, {"throttle": 0.2751779556274414, "steer": 0.04875843971967697, "brake": 0.0, "hand_brake": false, "reverse": false, "manual_gear_shift": false, "gear": 0, "frame": 175}, {"throttle": 0.29427370429039, "steer": 0.03664686903357506, "brake": 0.0, "hand_brake": false, "reverse": false, "manual_gear_shift": false, "gear": 0, "frame": 176}, {"throttle": 0.32070016860961914, "steer": 0.019619055092334747, "brake": 0.0, "hand_brake": false, "reverse": false, "manual_gear_shift": false, "gear": 0, "frame": 177}, {"throttle": 0.3497166037559509, "steer": -0.01958887279033661, "brake": 0.0, "hand_brake": false, "reverse": false, "manual_gear_shift": false, "gear": 0, "frame": 178}, {"throttle": 0.37447428703308105, "steer": -0.03038947656750679, "brake": 0.0, "hand_brake": false, "reverse": false, "manual_gear_shift": false, "gear": 0, "frame": 179}, {"throttle": 0.3854527175426483, "steer": -0.027167970314621925, "brake": 0.0, "hand_brake": false, "reverse": false, "manual_gear_shift": false, "gear": 0, "frame": 180}, {"throttle": 0.3890675902366638, "steer": -0.022234784439206123, "brake": 0.0, "hand_brake": false, "reverse": false, "manual_gear_shift": false, "gear": 0, "frame": 181}, {"throttle": 0.3876180052757263, "steer": -0.019661569967865944, "brake": 0.0, "hand_brake": false, "reverse": false, "manual_gear_shift": false, "gear": 0, "frame": 182}, {"throttle": 0.39581355452537537, "steer": -0.016332285478711128, "brake": 0.0, "hand_brake": false, "reverse": false, "manual_gear_shift": false, "gear": 0, "frame": 183}, {"throttle": 0.4161173105239868, "steer": -0.017224354669451714, "brake": 0.0, "hand_brake": false, "reverse": false, "manual_gear_shift": false, "gear": 0, "frame": 184}, {"throttle": 0.4501935839653015, "steer": -0.20467647910118103, "brake": 0.0, "hand_brake": false, "reverse": false, "manual_gear_shift": false, "gear": 0, "frame": 185}, {"throttle": 0.46743857860565186, "steer": -0.239150732755661, "brake": 0.0, "hand_brake": false, "reverse": false, "manual_gear_shift": false, "gear": 0, "frame": 186}, {"throttle": 0.49528127908706665, "steer": -0.25060176849365234, "brake": 0.0, "hand_brake": false, "reverse": false, "manual_gear_shift": false, "gear": 0, "frame": 187}, {"throttle": 0.5222362279891968, "steer": -0.2358372062444687, "brake": 0.0, "hand_brake": false, "reverse": false, "manual_gear_shift": false, "gear": 0, "frame": 188}, {"throttle": 0.5618022084236145, "steer": -0.2037518173456192, "brake": 0.0, "hand_brake": false, "reverse": false, "manual_gear_shift": false, "gear": 0, "frame": 189}, {"throttle": 0.5622814297676086, "steer": -0.15878023207187653, "brake": 0.0, "hand_brake": false, "reverse": false, "manual_gear_shift": false, "gear": 0, "frame": 190}, {"throttle": 0.5653112530708313, "steer": -0.10977783054113388, "brake": 0.0, "hand_brake": false, "reverse": false, "manual_gear_shift": false, "gear": 0, "frame": 191}, {"throttle": 0.5341593623161316, "steer": -0.06344784051179886, "brake": 0.0, "hand_brake": false, "reverse": false, "manual_gear_shift": false, "gear": 0, "frame": 192}, {"throttle": 0.498212605714798, "steer": -0.2634478509426117, "brake": 0.0, "hand_brake": false, "reverse": false, "manual_gear_shift": false, "gear": 0, "frame": 193}, {"throttle": 0.75, "steer": -0.25852373242378235, "brake": 0.0, "hand_brake": false, "reverse": false, "manual_gear_shift": false, "gear": 0, "frame": 194}, {"throttle": 0.75, "steer": -0.19265463948249817, "brake": 0.0, "hand_brake": false, "reverse": false, "manual_gear_shift": false, "gear": 0, "frame": 195}, {"throttle": 0.75, "steer": -0.13935156166553497, "brake": 0.0, "hand_brake": false, "reverse": false, "manual_gear_shift": false, "gear": 0, "frame": 196}, {"throttle": 0.7253174781799316, "steer": -0.15369489789009094, "brake": 0.0, "hand_brake": false, "reverse": false, "manual_gear_shift": false, "gear": 0, "frame": 197}, {"throttle": 0.6357097625732422, "steer": -0.14270232617855072, "brake": 0.0, "hand_brake": false, "reverse": false, "manual_gear_shift": false, "gear": 0, "frame": 198}, {"throttle": 0.5393140316009521, "steer": -0.15521904826164246, "brake": 0.0, "hand_brake": false, "reverse": false, "manual_gear_shift": false, "gear": 0, "frame": 199}, {"throttle": 0.4433731138706207, "steer": -0.255219042301178, "brake": 0.0, "hand_brake": false, "reverse": false, "manual_gear_shift": false, "gear": 0, "frame": 200}, {"throttle": 0.3808315694332123, "steer": -0.3552190363407135, "brake": 0.0, "hand_brake": false, "reverse": false, "manual_gear_shift": false, "gear": 0, "frame": 201}, {"throttle": 0.3553190231323242, "steer": -0.4552190601825714, "brake": 0.0, "hand_brake": false, "reverse": false, "manual_gear_shift": false, "gear": 0, "frame": 202}, {"throttle": 0.37055376172065735, "steer": -0.4559590220451355, "brake": 0.0, "hand_brake": false, "reverse": false, "manual_gear_shift": false, "gear": 0, "frame": 203}, {"throttle": 0.4037467837333679, "steer": -0.3559589982032776, "brake": 0.0, "hand_brake": false, "reverse": false, "manual_gear_shift": false, "gear": 0, "frame": 204}, {"throttle": 0.3700437545776367, "steer": -0.2924468517303467, "brake": 0.0, "hand_brake": false, "reverse": false, "manual_gear_shift": false, "gear": 0, "frame": 205}, {"throttle": 0.3598043620586395, "steer": -0.3924468457698822, "brake": 0.0, "hand_brake": false, "reverse": false, "manual_gear_shift": false, "gear": 0, "frame": 206}, {"throttle": 0.3963753283023834, "steer": -0.4924468398094177, "brake": 0.0, "hand_brake": false, "reverse": false, "manual_gear_shift": false, "gear": 0, "frame": 207}, {"throttle": 0.4309574067592621, "steer": -0.5924468636512756, "brake": 0.0, "hand_brake": false, "reverse": false, "manual_gear_shift": false, "gear": 0, "frame": 208}, {"throttle": 0.49191856384277344, "steer": -0.53976970911026, "brake": 0.0, "hand_brake": false, "reverse": false, "manual_gear_shift": false, "gear": 0, "frame": 209}, {"throttle": 0.5454409122467041, "steer": -0.4397696852684021, "brake": 0.0, "hand_brake": false, "reverse": false, "manual_gear_shift": false, "gear": 0, "frame": 210}, {"throttle": 0.5209108591079712, "steer": -0.3397696912288666, "brake": 0.0, "hand_brake": false, "reverse": false, "manual_gear_shift": false, "gear": 0, "frame": 211}, {"throttle": 0.519784688949585, "steer": -0.4397696852684021, "brake": 0.0, "hand_brake": false, "reverse": false, "manual_gear_shift": false, "gear": 0, "frame": 212}, {"throttle": 0.5343518853187561, "steer": -0.53976970911026, "brake": 0.0, "hand_brake": false, "reverse": false, "manual_gear_shift": false, "gear": 0, "frame": 213}, {"throttle": 0.4571627974510193, "steer": -0.5797415971755981, "brake": 0.0, "hand_brake": false, "reverse": false, "manual_gear_shift": false, "gear": 0, "frame": 214}, {"throttle": 0.44445306062698364, "steer": -0.5233108401298523, "brake": 0.0, "hand_brake": false, "reverse": false, "manual_gear_shift": false, "gear": 0, "frame": 215}, {"throttle": 0.46820786595344543, "steer": -0.4233108162879944, "brake": 0.0, "hand_brake": false, "reverse": false, "manual_gear_shift": false, "gear": 0, "frame": 216}, {"throttle": 0.4583362936973572, "steer": -0.32331082224845886, "brake": 0.0, "hand_brake": false, "reverse": false, "manual_gear_shift": false, "gear": 0, "frame": 217}, {"throttle": 0.4432376027107239, "steer": -0.22331081330776215, "brake": 0.0, "hand_brake": false, "reverse": false, "manual_gear_shift": false, "gear": 0, "frame": 218}, {"throttle": 0.37107381224632263, "steer": -0.12331081926822662, "brake": 0.0, "hand_brake": false, "reverse": false, "manual_gear_shift": false, "gear": 0, "frame": 219}, {"throttle": 0.3199158012866974, "steer": -0.04707122594118118, "brake": 0.0, "hand_brake": false, "reverse": false, "manual_gear_shift": false, "gear": 0, "frame": 220}, {"throttle": 0.3050249218940735, "steer": -0.1470712274312973, "brake": 0.0, "hand_brake": false, "reverse": false, "manual_gear_shift": false, "gear": 0, "frame": 221}, {"throttle": 0.329509973526001, "steer": -0.24707122147083282, "brake": 0.0, "hand_brake": false, "reverse": false, "manual_gear_shift": false, "gear": 0, "frame": 222}, {"throttle": 0.3721325993537903, "steer": -0.23654134571552277, "brake": 0.0, "hand_brake": false, "reverse": false, "manual_gear_shift": false, "gear": 0, "frame": 223}, {"throttle": 0.44232994318008423, "steer": -0.13654135167598724, "brake": 0.0, "hand_brake": false, "reverse": false, "manual_gear_shift": false, "gear": 0, "frame": 224}, {"throttle": 0.44044625759124756, "steer": -0.07393454760313034, "brake": 0.0, "hand_brake": false, "reverse": false, "manual_gear_shift": false, "gear": 0, "frame": 225}, {"throttle": 0.44818931818008423, "steer": -0.17393454909324646, "brake": 0.0, "hand_brake": false, "reverse": false, "manual_gear_shift": false, "gear": 0, "frame": 226}, {"throttle": 0.44476673007011414, "steer": -0.17361855506896973, "brake": 0.0, "hand_brake": false, "reverse": false, "manual_gear_shift": false, "gear": 0, "frame": 227}, {"throttle": 0.42799296975135803, "steer": -0.13770170509815216, "brake": 0.0, "hand_brake": false, "reverse": false, "manual_gear_shift": false, "gear": 0, "frame": 228}, {"throttle": 0.40364423394203186, "steer": -0.12629781663417816, "brake": 0.0, "hand_brake": false, "reverse": false, "manual_gear_shift": false, "gear": 0, "frame": 229}, {"throttle": 0.3950345814228058, "steer": -0.09309758991003036, "brake": 0.0, "hand_brake": false, "reverse": false, "manual_gear_shift": false, "gear": 0, "frame": 230}, {"throttle": 0.381497859954834, "steer": -0.09518913179636002, "brake": 0.0, "hand_brake": false, "reverse": false, "manual_gear_shift": false, "gear": 0, "frame": 231}, {"throttle": 0.3777494728565216, "steer": -0.19518913328647614, "brake": 0.0, "hand_brake": false, "reverse": false, "manual_gear_shift": false, "gear": 0, "frame": 232}, {"throttle": 0.36845663189888, "steer": -0.17995642125606537, "brake": 0.0, "hand_brake": false, "reverse": false, "manual_gear_shift": false, "gear": 0, "frame": 233}, {"throttle": 0.3748951554298401, "steer": -0.15061205625534058, "brake": 0.0, "hand_brake": false, "reverse": false, "manual_gear_shift": false, "gear": 0, "frame": 234}, {"throttle": 0.37417349219322205, "steer": -0.116547591984272, "brake": 0.0, "hand_brake": false, "reverse": false, "manual_gear_shift": false, "gear": 0, "frame": 235}, {"throttle": 0.362752228975296, "steer": -0.07691903412342072, "brake": 0.0, "hand_brake": false, "reverse": false, "manual_gear_shift": false, "gear": 0, "frame": 236}, {"throttle": 0.35233068466186523, "steer": -0.17691902816295624, "brake": 0.0, "hand_brake": false, "reverse": false, "manual_gear_shift": false, "gear": 0, "frame": 237}, {"throttle": 0.37233617901802063, "steer": -0.07691903412342072, "brake": 0.0, "hand_brake": false, "reverse": false, "manual_gear_shift": false, "gear": 0, "frame": 238}, {"throttle": 0.35768428444862366, "steer": -0.0030930081848055124, "brake": 0.0, "hand_brake": false, "reverse": false, "manual_gear_shift": false, "gear": 0, "frame": 239}, {"throttle": 0.35066407918930054, "steer": -0.0026116403751075268, "brake": 0.0, "hand_brake": false, "reverse": false, "manual_gear_shift": false, "gear": 0, "frame": 240}, {"throttle": 0.3447287976741791, "steer": -0.004031976219266653, "brake": 0.0, "hand_brake": false, "reverse": false, "manual_gear_shift": false, "gear": 0, "frame": 241}, {"throttle": 0.3512525260448456, "steer": -0.01344346534460783, "brake": 0.0, "hand_brake": false, "reverse": false, "manual_gear_shift": false, "gear": 0, "frame": 242}, {"throttle": 0.35649046301841736, "steer": -0.11344346404075623, "brake": 0.0, "hand_brake": false, "reverse": false, "manual_gear_shift": false, "gear": 0, "frame": 243}, {"throttle": 0.3697431683540344, "steer": -0.0992572009563446, "brake": 0.0, "hand_brake": false, "reverse": false, "manual_gear_shift": false, "gear": 0, "frame": 244}, {"throttle": 0.39692071080207825, "steer": -0.061848241835832596, "brake": 0.0, "hand_brake": false, "reverse": false, "manual_gear_shift": false, "gear": 0, "frame": 245}, {"throttle": 0.4136466979980469, "steer": -0.0164576955139637, "brake": 0.0, "hand_brake": false, "reverse": false, "manual_gear_shift": false, "gear": 0, "frame": 246}, {"throttle": 0.43635550141334534, "steer": 0.02062714286148548, "brake": 0.0, "hand_brake": false, "reverse": false, "manual_gear_shift": false, "gear": 0, "frame": 247}, {"throttle": 0.43255317211151123, "steer": 0.044596459716558456, "brake": 0.0, "hand_brake": false, "reverse": false, "manual_gear_shift": false, "gear": 0, "frame": 248}, {"throttle": 0.42891785502433777, "steer": -0.055403538048267365, "brake": 0.0, "hand_brake": false, "reverse": false, "manual_gear_shift": false, "gear": 0, "frame": 249}, {"throttle": 0.4206683337688446, "steer": -0.11111020296812057, "brake": 0.0, "hand_brake": false, "reverse": false, "manual_gear_shift": false, "gear": 0, "frame": 250}, {"throttle": 0.40957292914390564, "steer": -0.12642115354537964, "brake": 0.0, "hand_brake": false, "reverse": false, "manual_gear_shift": false, "gear": 0, "frame": 251}, {"throttle": 0.3957560062408447, "steer": -0.10057983547449112, "brake": 0.0, "hand_brake": false, "reverse": false, "manual_gear_shift": false, "gear": 0, "frame": 252}, {"throttle": 0.39285707473754883, "steer": -0.08352277427911758, "brake": 0.0, "hand_brake": false, "reverse": false, "manual_gear_shift": false, "gear": 0, "frame": 253}, {"throttle": 0.4021961987018585, "steer": -0.03315439075231552, "brake": 0.0, "hand_brake": false, "reverse": false, "manual_gear_shift": false, "gear": 0, "frame": 254}, {"throttle": 0.40960294008255005, "steer": -0.11128874868154526, "brake": 0.0, "hand_brake": false, "reverse": false, "manual_gear_shift": false, "gear": 0, "frame": 255}, {"throttle": 0.4289746880531311, "steer": -0.05625076964497566, "brake": 0.0, "hand_brake": false, "reverse": false, "manual_gear_shift": false, "gear": 0, "frame": 256}, {"throttle": 0.4280434846878052, "steer": -0.02724139206111431, "brake": 0.0, "hand_brake": false, "reverse": false, "manual_gear_shift": false, "gear": 0, "frame": 257}, {"throttle": 0.4236930012702942, "steer": -0.038690198212862015, "brake": 0.0, "hand_brake": false, "reverse": false, "manual_gear_shift": false, "gear": 0, "frame": 258}, {"throttle": 0.4085130989551544, "steer": -0.050631333142519, "brake": 0.0, "hand_brake": false, "reverse": false, "manual_gear_shift": false, "gear": 0, "frame": 259}, {"throttle": 0.3850839138031006, "steer": -0.08241858333349228, "brake": 0.0, "hand_brake": false, "reverse": false, "manual_gear_shift": false, "gear": 0, "frame": 260}, {"throttle": 0.3697618842124939, "steer": -0.05014023557305336, "brake": 0.0, "hand_brake": false, "reverse": false, "manual_gear_shift": false, "gear": 0, "frame": 261}, {"throttle": 0.3569924533367157, "steer": -0.03670087456703186, "brake": 0.0, "hand_brake": false, "reverse": false, "manual_gear_shift": false, "gear": 0, "frame": 262}, {"throttle": 0.3460904061794281, "steer": -0.046489108353853226, "brake": 0.0, "hand_brake": false, "reverse": false, "manual_gear_shift": false, "gear": 0, "frame": 263}, {"throttle": 0.3400859832763672, "steer": -0.06458350270986557, "brake": 0.0, "hand_brake": false, "reverse": false, "manual_gear_shift": false, "gear": 0, "frame": 264}, {"throttle": 0.33807066082954407, "steer": -0.09009017050266266, "brake": 0.0, "hand_brake": false, "reverse": false, "manual_gear_shift": false, "gear": 0, "frame": 265}, {"throttle": 0.3468644917011261, "steer": -0.11223766207695007, "brake": 0.0, "hand_brake": false, "reverse": false, "manual_gear_shift": false, "gear": 0, "frame": 266}, {"throttle": 0.3690410256385803, "steer": -0.06916912645101547, "brake": 0.0, "hand_brake": false, "reverse": false, "manual_gear_shift": false, "gear": 0, "frame": 267}, {"throttle": 0.36601194739341736, "steer": -0.04453662782907486, "brake": 0.0, "hand_brake": false, "reverse": false, "manual_gear_shift": false, "gear": 0, "frame": 268}, {"throttle": 0.3656769096851349, "steer": -0.03824833407998085, "brake": 0.0, "hand_brake": false, "reverse": false, "manual_gear_shift": false, "gear": 0, "frame": 269}, {"throttle": 0.3666227459907532, "steer": 0.020461497828364372, "brake": 0.0, "hand_brake": false, "reverse": false, "manual_gear_shift": false, "gear": 0, "frame": 270}, {"throttle": 0.3640751540660858, "steer": 0.021345749497413635, "brake": 0.0, "hand_brake": false, "reverse": false, "manual_gear_shift": false, "gear": 0, "frame": 271}, {"throttle": 0.3738495707511902, "steer": -0.059417735785245895, "brake": 0.0, "hand_brake": false, "reverse": false, "manual_gear_shift": false, "gear": 0, "frame": 272}, {"throttle": 0.4037308990955353, "steer": -0.1071404367685318, "brake": 0.0, "hand_brake": false, "reverse": false, "manual_gear_shift": false, "gear": 0, "frame": 273}, {"throttle": 0.3965142071247101, "steer": -0.14415371417999268, "brake": 0.0, "hand_brake": false, "reverse": false, "manual_gear_shift": false, "gear": 0, "frame": 274}, {"throttle": 0.39955294132232666, "steer": -0.09625624120235443, "brake": 0.0, "hand_brake": false, "reverse": false, "manual_gear_shift": false, "gear": 0, "frame": 275}, {"throttle": 0.39263877272605896, "steer": -0.044611960649490356, "brake": 0.0, "hand_brake": false, "reverse": false, "manual_gear_shift": false, "gear": 0, "frame": 276}, {"throttle": 0.4053678512573242, "steer": -0.0670609176158905, "brake": 0.0, "hand_brake": false, "reverse": false, "manual_gear_shift": false, "gear": 0, "frame": 277}, {"throttle": 0.3977600038051605, "steer": -0.08695370703935623, "brake": 0.0, "hand_brake": false, "reverse": false, "manual_gear_shift": false, "gear": 0, "frame": 278}, {"throttle": 0.3894578218460083, "steer": -0.07215984165668488, "brake": 0.0, "hand_brake": false, "reverse": false, "manual_gear_shift": false, "gear": 0, "frame": 279}, {"throttle": 0.3806591033935547, "steer": -0.0658642053604126, "brake": 0.0, "hand_brake": false, "reverse": false, "manual_gear_shift": false, "gear": 0, "frame": 280}, {"throttle": 0.3769164979457855, "steer": -0.06259747594594955, "brake": 0.0, "hand_brake": false, "reverse": false, "manual_gear_shift": false, "gear": 0, "frame": 281}, {"throttle": 0.3693552315235138, "steer": -0.06118520721793175, "brake": 0.0, "hand_brake": false, "reverse": false, "manual_gear_shift": false, "gear": 0, "frame": 282}, {"throttle": 0.36740896105766296, "steer": -0.05634962394833565, "brake": 0.0, "hand_brake": false, "reverse": false, "manual_gear_shift": false, "gear": 0, "frame": 283}, {"throttle": 0.3779556155204773, "steer": -0.03399056941270828, "brake": 0.0, "hand_brake": false, "reverse": false, "manual_gear_shift": false, "gear": 0, "frame": 284}, {"throttle": 0.3848601281642914, "steer": -0.026024222373962402, "brake": 0.0, "hand_brake": false, "reverse": false, "manual_gear_shift": false, "gear": 0, "frame": 285}, {"throttle": 0.39357638359069824, "steer": -0.04046126827597618, "brake": 0.0, "hand_brake": false, "reverse": false, "manual_gear_shift": false, "gear": 0, "frame": 286}, {"throttle": 0.41194573044776917, "steer": -0.06799411028623581, "brake": 0.0, "hand_brake": false, "reverse": false, "manual_gear_shift": false, "gear": 0, "frame": 287}, {"throttle": 0.41476085782051086, "steer": -0.0756402313709259, "brake": 0.0, "hand_brake": false, "reverse": false, "manual_gear_shift": false, "gear": 0, "frame": 288}, {"throttle": 0.41295546293258667, "steer": -0.05248084291815758, "brake": 0.0, "hand_brake": false, "reverse": false, "manual_gear_shift": false, "gear": 0, "frame": 289}, {"throttle": 0.4141482710838318, "steer": -0.08331591635942459, "brake": 0.0, "hand_brake": false, "reverse": false, "manual_gear_shift": false, "gear": 0, "frame": 290}, {"throttle": 0.4046173393726349, "steer": -0.10383094847202301, "brake": 0.0, "hand_brake": false, "reverse": false, "manual_gear_shift": false, "gear": 0, "frame": 291}, {"throttle": 0.3979695439338684, "steer": -0.07493671029806137, "brake": 0.0, "hand_brake": false, "reverse": false, "manual_gear_shift": false, "gear": 0, "frame": 292}, {"throttle": 0.40071815252304077, "steer": -0.01988411508500576, "brake": 0.0, "hand_brake": false, "reverse": false, "manual_gear_shift": false, "gear": 0, "frame": 293}, {"throttle": 0.39250048995018005, "steer": -0.004323686007410288, "brake": 0.0, "hand_brake": false, "reverse": false, "manual_gear_shift": false, "gear": 0, "frame": 294}, {"throttle": 0.3871683180332184, "steer": 0.0046850405633449554, "brake": 0.0, "hand_brake": false, "reverse": false, "manual_gear_shift": false, "gear": 0, "frame": 295}, {"throttle": 0.3828563988208771, "steer": -0.0007284854655154049, "brake": 0.0, "hand_brake": false, "reverse": false, "manual_gear_shift": false, "gear": 0, "frame": 296}, {"throttle": 0.3758417069911957, "steer": -0.03138378635048866, "brake": 0.0, "hand_brake": false, "reverse": false, "manual_gear_shift": false, "gear": 0, "frame": 297}, {"throttle": 0.3701704144477844, "steer": -0.048826705664396286, "brake": 0.0, "hand_brake": false, "reverse": false, "manual_gear_shift": false, "gear": 0, "frame": 298}, {"throttle": 0.35758358240127563, "steer": -0.0833355113863945, "brake": 0.0, "hand_brake": false, "reverse": false, "manual_gear_shift": false, "gear": 0, "frame": 299}, {"throttle": 0.3512120544910431, "steer": -0.03843839839100838, "brake": 0.0, "hand_brake": false, "reverse": false, "manual_gear_shift": false, "gear": 0, "frame": 300}, {"throttle": 0.0, "steer": -0.03272005170583725, "brake": 0.050085775554180145, "hand_brake": false, "reverse": false, "manual_gear_shift": false, "gear": 0, "frame": 301}, {"throttle": 0.0, "steer": -0.022954342886805534, "brake": 0.03198244050145149, "hand_brake": false, "reverse": false, "manual_gear_shift": false, "gear": 0, "frame": 302}, {"throttle": 0.026111550629138947, "steer": -0.03279198706150055, "brake": 0.0, "hand_brake": false, "reverse": false, "manual_gear_shift": false, "gear": 0, "frame": 303}, {"throttle": 0.08001823723316193, "steer": -0.05013938620686531, "brake": 0.0, "hand_brake": false, "reverse": false, "manual_gear_shift": false, "gear": 0, "frame": 304}, {"throttle": 0.1424974501132965, "steer": -0.05869995430111885, "brake": 0.0, "hand_brake": false, "reverse": false, "manual_gear_shift": false, "gear": 0, "frame": 305}, {"throttle": 0.2209916114807129, "steer": -0.04612899571657181, "brake": 0.0, "hand_brake": false, "reverse": false, "manual_gear_shift": false, "gear": 0, "frame": 306}, {"throttle": 0.29017341136932373, "steer": -0.019762670621275902, "brake": 0.0, "hand_brake": false, "reverse": false, "manual_gear_shift": false, "gear": 0, "frame": 307}, {"throttle": 0.3623930811882019, "steer": -0.010583359748125076, "brake": 0.0, "hand_brake": false, "reverse": false, "manual_gear_shift": false, "gear": 0, "frame": 308}, {"throttle": 0.4395750164985657, "steer": -0.01683751493692398, "brake": 0.0, "hand_brake": false, "reverse": false, "manual_gear_shift": false, "gear": 0, "frame": 309}, {"throttle": 0.4953720271587372, "steer": -0.022992242127656937, "brake": 0.0, "hand_brake": false, "reverse": false, "manual_gear_shift": false, "gear": 0, "frame": 310}, {"throttle": 0.5230333209037781, "steer": -0.025424063205718994, "brake": 0.0, "hand_brake": false, "reverse": false, "manual_gear_shift": false, "gear": 0, "frame": 311}, {"throttle": 0.5326715707778931, "steer": -0.024918289855122566, "brake": 0.0, "hand_brake": false, "reverse": false, "manual_gear_shift": false, "gear": 0, "frame": 312}, {"throttle": 0.5335417985916138, "steer": -0.01853792555630207, "brake": 0.0, "hand_brake": false, "reverse": false, "manual_gear_shift": false, "gear": 0, "frame": 313}, {"throttle": 0.5096740126609802, "steer": 0.006799662485718727, "brake": 0.0, "hand_brake": false, "reverse": false, "manual_gear_shift": false, "gear": 0, "frame": 314}, {"throttle": 0.4893356263637543, "steer": 0.02716687321662903, "brake": 0.0, "hand_brake": false, "reverse": false, "manual_gear_shift": false, "gear": 0, "frame": 315}, {"throttle": 0.47226622700691223, "steer": 0.04224170744419098, "brake": 0.0, "hand_brake": false, "reverse": false, "manual_gear_shift": false, "gear": 0, "frame": 316}, {"throttle": 0.44274312257766724, "steer": 0.044821564108133316, "brake": 0.0, "hand_brake": false, "reverse": false, "manual_gear_shift": false, "gear": 0, "frame": 317}, {"throttle": 0.408886581659317, "steer": 0.04628715664148331, "brake": 0.0, "hand_brake": false, "reverse": false, "manual_gear_shift": false, "gear": 0, "frame": 318}, {"throttle": 0.39712950587272644, "steer": 0.03698865324258804, "brake": 0.0, "hand_brake": false, "reverse": false, "manual_gear_shift": false, "gear": 0, "frame": 319}, {"throttle": 0.39618217945098877, "steer": 0.0252127256244421, "brake": 0.0, "hand_brake": false, "reverse": false, "manual_gear_shift": false, "gear": 0, "frame": 320}, {"throttle": 0.39650702476501465, "steer": 0.015234129503369331, "brake": 0.0, "hand_brake": false, "reverse": false, "manual_gear_shift": false, "gear": 0, "frame": 321}, {"throttle": 0.41769614815711975, "steer": 0.021780788898468018, "brake": 0.0, "hand_brake": false, "reverse": false, "manual_gear_shift": false, "gear": 0, "frame": 322}, {"throttle": 0.44795119762420654, "steer": 0.04567838832736015, "brake": 0.0, "hand_brake": false, "reverse": false, "manual_gear_shift": false, "gear": 0, "frame": 323}, {"throttle": 0.4601176381111145, "steer": 0.0699751153588295, "brake": 0.0, "hand_brake": false, "reverse": false, "manual_gear_shift": false, "gear": 0, "frame": 324}, {"throttle": 0.48395150899887085, "steer": 0.06724291294813156, "brake": 0.0, "hand_brake": false, "reverse": false, "manual_gear_shift": false, "gear": 0, "frame": 325}, {"throttle": 0.4997665584087372, "steer": 0.04486139491200447, "brake": 0.0, "hand_brake": false, "reverse": false, "manual_gear_shift": false, "gear": 0, "frame": 326}, {"throttle": 0.4823727607727051, "steer": 0.020600927993655205, "brake": 0.0, "hand_brake": false, "reverse": false, "manual_gear_shift": false, "gear": 0, "frame": 327}, {"throttle": 0.46421846747398376, "steer": 0.012727810069918633, "brake": 0.0, "hand_brake": false, "reverse": false, "manual_gear_shift": false, "gear": 0, "frame": 328}, {"throttle": 0.4414892792701721, "steer": -0.028715230524539948, "brake": 0.0, "hand_brake": false, "reverse": false, "manual_gear_shift": false, "gear": 0, "frame": 329}, {"throttle": 0.42665231227874756, "steer": -0.02208259515464306, "brake": 0.0, "hand_brake": false, "reverse": false, "manual_gear_shift": false, "gear": 0, "frame": 330}, {"throttle": 0.41856619715690613, "steer": 0.0010539965005591512, "brake": 0.0, "hand_brake": false, "reverse": false, "manual_gear_shift": false, "gear": 0, "frame": 331}, {"throttle": 0.3834855854511261, "steer": 0.03058573231101036, "brake": 0.0, "hand_brake": false, "reverse": false, "manual_gear_shift": false, "gear": 0, "frame": 332}, {"throttle": 0.36936357617378235, "steer": 0.04413653910160065, "brake": 0.0, "hand_brake": false, "reverse": false, "manual_gear_shift": false, "gear": 0, "frame": 333}, {"throttle": 0.36090439558029175, "steer": 0.03735329955816269, "brake": 0.0, "hand_brake": false, "reverse": false, "manual_gear_shift": false, "gear": 0, "frame": 334}, {"throttle": 0.356629341840744, "steer": 0.015173370018601418, "brake": 0.0, "hand_brake": false, "reverse": false, "manual_gear_shift": false, "gear": 0, "frame": 335}, {"throttle": 0.3436429798603058, "steer": -0.18482662737369537, "brake": 0.0, "hand_brake": false, "reverse": false, "manual_gear_shift": false, "gear": 0, "frame": 336}, {"throttle": 0.3428499400615692, "steer": -0.23611795902252197, "brake": 0.0, "hand_brake": false, "reverse": false, "manual_gear_shift": false, "gear": 0, "frame": 337}, {"throttle": 0.3729306161403656, "steer": -0.22511222958564758, "brake": 0.0, "hand_brake": false, "reverse": false, "manual_gear_shift": false, "gear": 0, "frame": 338}, {"throttle": 0.3810012936592102, "steer": -0.20297332108020782, "brake": 0.0, "hand_brake": false, "reverse": false, "manual_gear_shift": false, "gear": 0, "frame": 339}, {"throttle": 0.37065595388412476, "steer": -0.18244969844818115, "brake": 0.0, "hand_brake": false, "reverse": false, "manual_gear_shift": false, "gear": 0, "frame": 340}, {"throttle": 0.37044790387153625, "steer": -0.16425389051437378, "brake": 0.0, "hand_brake": false, "reverse": false, "manual_gear_shift": false, "gear": 0, "frame": 341}, {"throttle": 0.3717917501926422, "steer": -0.15391553938388824, "brake": 0.0, "hand_brake": false, "reverse": false, "manual_gear_shift": false, "gear": 0, "frame": 342}, {"throttle": 0.38131147623062134, "steer": -0.14955806732177734, "brake": 0.0, "hand_brake": false, "reverse": false, "manual_gear_shift": false, "gear": 0, "frame": 343}, {"throttle": 0.41522642970085144, "steer": -0.3495580852031708, "brake": 0.0, "hand_brake": false, "reverse": false, "manual_gear_shift": false, "gear": 0, "frame": 344}, {"throttle": 0.47479769587516785, "steer": -0.4295252561569214, "brake": 0.0, "hand_brake": false, "reverse": false, "manual_gear_shift": false, "gear": 0, "frame": 345}, {"throttle": 0.5515614151954651, "steer": -0.3718782067298889, "brake": 0.0, "hand_brake": false, "reverse": false, "manual_gear_shift": false, "gear": 0, "frame": 346}, {"throttle": 0.5834607481956482, "steer": -0.3010428845882416, "brake": 0.0, "hand_brake": false, "reverse": false, "manual_gear_shift": false, "gear": 0, "frame": 347}, {"throttle": 0.5924421548843384, "steer": -0.2218795120716095, "brake": 0.0, "hand_brake": false, "reverse": false, "manual_gear_shift": false, "gear": 0, "frame": 348}, {"throttle": 0.5999330282211304, "steer": -0.13562935590744019, "brake": 0.0, "hand_brake": false, "reverse": false, "manual_gear_shift": false, "gear": 0, "frame": 349}, {"throttle": 0.5587214827537537, "steer": -0.05051961913704872, "brake": 0.0, "hand_brake": false, "reverse": false, "manual_gear_shift": false, "gear": 0, "frame": 350}, {"throttle": 0.5110130310058594, "steer": 0.017531316727399826, "brake": 0.0, "hand_brake": false, "reverse": false, "manual_gear_shift": false, "gear": 0, "frame": 351}, {"throttle": 0.4631805717945099, "steer": -0.18246868252754211, "brake": 0.0, "hand_brake": false, "reverse": false, "manual_gear_shift": false, "gear": 0, "frame": 352}, {"throttle": 0.75, "steer": -0.28246867656707764, "brake": 0.0, "hand_brake": false, "reverse": false, "manual_gear_shift": false, "gear": 0, "frame": 353}, {"throttle": 0.75, "steer": -0.24221177399158478, "brake": 0.0, "hand_brake": false, "reverse": false, "manual_gear_shift": false, "gear": 0, "frame": 354}, {"throttle": 0.7074058055877686, "steer": -0.21006841957569122, "brake": 0.0, "hand_brake": false, "reverse": false, "manual_gear_shift": false, "gear": 0, "frame": 355}, {"throttle": 0.6257959604263306, "steer": -0.19525146484375, "brake": 0.0, "hand_brake": false, "reverse": false, "manual_gear_shift": false, "gear": 0, "frame": 356}, {"throttle": 0.5783004760742188, "steer": -0.2952514588832855, "brake": 0.0, "hand_brake": false, "reverse": false, "manual_gear_shift": false, "gear": 0, "frame": 357}, {"throttle": 0.5004240870475769, "steer": -0.39525148272514343, "brake": 0.0, "hand_brake": false, "reverse": false, "manual_gear_shift": false, "gear": 0, "frame": 358}, {"throttle": 0.4762324392795563, "steer": -0.33576545119285583, "brake": 0.0, "hand_brake": false, "reverse": false, "manual_gear_shift": false, "gear": 0, "frame": 359}, {"throttle": 0.49664783477783203, "steer": -0.23576544225215912, "brake": 0.0, "hand_brake": false, "reverse": false, "manual_gear_shift": false, "gear": 0, "frame": 360}, {"throttle": 0.43932822346687317, "steer": -0.1357654333114624, "brake": 0.0, "hand_brake": false, "reverse": false, "manual_gear_shift": false, "gear": 0, "frame": 361}, {"throttle": 0.38381367921829224, "steer": -0.23576544225215912, "brake": 0.0, "hand_brake": false, "reverse": false, "manual_gear_shift": false, "gear": 0, "frame": 362}, {"throttle": 0.3534657061100006, "steer": -0.33576545119285583, "brake": 0.0, "hand_brake": false, "reverse": false, "manual_gear_shift": false, "gear": 0, "frame": 363}, {"throttle": 0.3273896872997284, "steer": -0.43576544523239136, "brake": 0.0, "hand_brake": false, "reverse": false, "manual_gear_shift": false, "gear": 0, "frame": 364}, {"throttle": 0.3281312882900238, "steer": -0.4273386001586914, "brake": 0.0, "hand_brake": false, "reverse": false, "manual_gear_shift": false, "gear": 0, "frame": 365}, {"throttle": 0.36471039056777954, "steer": -0.34426581859588623, "brake": 0.0, "hand_brake": false, "reverse": false, "manual_gear_shift": false, "gear": 0, "frame": 366}, {"throttle": 0.3445155620574951, "steer": -0.277730256319046, "brake": 0.0, "hand_brake": false, "reverse": false, "manual_gear_shift": false, "gear": 0, "frame": 367}, {"throttle": 0.356062650680542, "steer": -0.37773025035858154, "brake": 0.0, "hand_brake": false, "reverse": false, "manual_gear_shift": false, "gear": 0, "frame": 368}, {"throttle": 0.43043017387390137, "steer": -0.47773024439811707, "brake": 0.0, "hand_brake": false, "reverse": false, "manual_gear_shift": false, "gear": 0, "frame": 369}, {"throttle": 0.453890860080719, "steer": -0.4671206772327423, "brake": 0.0, "hand_brake": false, "reverse": false, "manual_gear_shift": false, "gear": 0, "frame": 370}, {"throttle": 0.5149587392807007, "steer": -0.3738367557525635, "brake": 0.0, "hand_brake": false, "reverse": false, "manual_gear_shift": false, "gear": 0, "frame": 371}, {"throttle": 0.509834885597229, "steer": -0.2751685380935669, "brake": 0.0, "hand_brake": false, "reverse": false, "manual_gear_shift": false, "gear": 0, "frame": 372}, {"throttle": 0.48250454664230347, "steer": -0.22810059785842896, "brake": 0.0, "hand_brake": false, "reverse": false, "manual_gear_shift": false, "gear": 0, "frame": 373}, {"throttle": 0.484849214553833, "steer": -0.15343521535396576, "brake": 0.0, "hand_brake": false, "reverse": false, "manual_gear_shift": false, "gear": 0, "frame": 374}, {"throttle": 0.43906405568122864, "steer": -0.1030483990907669, "brake": 0.0, "hand_brake": false, "reverse": false, "manual_gear_shift": false, "gear": 0, "frame": 375}, {"throttle": 0.4193343222141266, "steer": -0.11604595929384232, "brake": 0.0, "hand_brake": false, "reverse": false, "manual_gear_shift": false, "gear": 0, "frame": 376}, {"throttle": 0.39195388555526733, "steer": -0.13480275869369507, "brake": 0.0, "hand_brake": false, "reverse": false, "manual_gear_shift": false, "gear": 0, "frame": 377}, {"throttle": 0.3732238709926605, "steer": -0.23480276763439178, "brake": 0.0, "hand_brake": false, "reverse": false, "manual_gear_shift": false, "gear": 0, "frame": 378}, {"throttle": 0.35822027921676636, "steer": -0.2743498384952545, "brake": 0.0, "hand_brake": false, "reverse": false, "manual_gear_shift": false, "gear": 0, "frame": 379}, {"throttle": 0.359136164188385, "steer": -0.2651904225349426, "brake": 0.0, "hand_brake": false, "reverse": false, "manual_gear_shift": false, "gear": 0, "frame": 380}, {"throttle": 0.3900182843208313, "steer": -0.25241878628730774, "brake": 0.0, "hand_brake": false, "reverse": false, "manual_gear_shift": false, "gear": 0, "frame": 381}, {"throttle": 0.4491710960865021, "steer": -0.17471405863761902, "brake": 0.0, "hand_brake": false, "reverse": false, "manual_gear_shift": false, "gear": 0, "frame": 382}, {"throttle": 0.4617598354816437, "steer": -0.10578226298093796, "brake": 0.0, "hand_brake": false, "reverse": false, "manual_gear_shift": false, "gear": 0, "frame": 383}, {"throttle": 0.45460614562034607, "steer": -0.20578226447105408, "brake": 0.0, "hand_brake": false, "reverse": false, "manual_gear_shift": false, "gear": 0, "frame": 384}, {"throttle": 0.4394303560256958, "steer": -0.2130967378616333, "brake": 0.0, "hand_brake": false, "reverse": false, "manual_gear_shift": false, "gear": 0, "frame": 385}, {"throttle": 0.4441930949687958, "steer": -0.187315434217453, "brake": 0.0, "hand_brake": false, "reverse": false, "manual_gear_shift": false, "gear": 0, "frame": 386}, {"throttle": 0.4680533707141876, "steer": -0.117061547935009, "brake": 0.0, "hand_brake": false, "reverse": false, "manual_gear_shift": false, "gear": 0, "frame": 387}, {"throttle": 0.4440157115459442, "steer": -0.06503234803676605, "brake": 0.0, "hand_brake": false, "reverse": false, "manual_gear_shift": false, "gear": 0, "frame": 388}, {"throttle": 0.4262417256832123, "steer": -0.16503234207630157, "brake": 0.0, "hand_brake": false, "reverse": false, "manual_gear_shift": false, "gear": 0, "frame": 389}, {"throttle": 0.4287564754486084, "steer": -0.1968764364719391, "brake": 0.0, "hand_brake": false, "reverse": false, "manual_gear_shift": false, "gear": 0, "frame": 390}, {"throttle": 0.45175105333328247, "steer": -0.15493209660053253, "brake": 0.0, "hand_brake": false, "reverse": false, "manual_gear_shift": false, "gear": 0, "frame": 391}, {"throttle": 0.469851553440094, "steer": -0.07857999950647354, "brake": 0.0, "hand_brake": false, "reverse": false, "manual_gear_shift": false, "gear": 0, "frame": 392}, {"throttle": 0.47328466176986694, "steer": -0.014486989006400108, "brake": 0.0, "hand_brake": false, "reverse": false, "manual_gear_shift": false, "gear": 0, "frame": 393}, {"throttle": 0.44522374868392944, "steer": 0.01104468572884798, "brake": 0.0, "hand_brake": false, "reverse": false, "manual_gear_shift": false, "gear": 0, "frame": 394}, {"throttle": 0.4037632942199707, "steer": -0.08895531296730042, "brake": 0.0, "hand_brake": false, "reverse": false, "manual_gear_shift": false, "gear": 0, "frame": 395}, {"throttle": 0.38030150532722473, "steer": -0.05324070528149605, "brake": 0.0, "hand_brake": false, "reverse": false, "manual_gear_shift": false, "gear": 0, "frame": 396}, {"throttle": 0.3587878346443176, "steer": -0.032554201781749725, "brake": 0.0, "hand_brake": false, "reverse": false, "manual_gear_shift": false, "gear": 0, "frame": 397}, {"throttle": 0.3572821319103241, "steer": -0.0053688460029661655, "brake": 0.0, "hand_brake": false, "reverse": false, "manual_gear_shift": false, "gear": 0, "frame": 398}, {"throttle": 0.3720748722553253, "steer": -0.02617538906633854, "brake": 0.0, "hand_brake": false, "reverse": false, "manual_gear_shift": false, "gear": 0, "frame": 399}, {"throttle": 0.3778495490550995, "steer": -0.045014508068561554, "brake": 0.0, "hand_brake": false, "reverse": false, "manual_gear_shift": false, "gear": 0, "frame": 400}, {"throttle": 0.38630494475364685, "steer": -0.14501450955867767, "brake": 0.0, "hand_brake": false, "reverse": false, "manual_gear_shift": false, "gear": 0, "frame": 401}, {"throttle": 0.3937901556491852, "steer": -0.045014508068561554, "brake": 0.0, "hand_brake": false, "reverse": false, "manual_gear_shift": false, "gear": 0, "frame": 402}, {"throttle": 0.39701467752456665, "steer": -0.024591095745563507, "brake": 0.0, "hand_brake": false, "reverse": false, "manual_gear_shift": false, "gear": 0, "frame": 403}, {"throttle": 0.39230889081954956, "steer": -0.02054438181221485, "brake": 0.0, "hand_brake": false, "reverse": false, "manual_gear_shift": false, "gear": 0, "frame": 404}, {"throttle": 0.3977494537830353, "steer": -0.045256540179252625, "brake": 0.0, "hand_brake": false, "reverse": false, "manual_gear_shift": false, "gear": 0, "frame": 405}, {"throttle": 0.40841028094291687, "steer": -0.0740177184343338, "brake": 0.0, "hand_brake": false, "reverse": false, "manual_gear_shift": false, "gear": 0, "frame": 406}, {"throttle": 0.42498666048049927, "steer": -0.16801509261131287, "brake": 0.0, "hand_brake": false, "reverse": false, "manual_gear_shift": false, "gear": 0, "frame": 407}, {"throttle": 0.4546548128128052, "steer": -0.06801509112119675, "brake": 0.0, "hand_brake": false, "reverse": false, "manual_gear_shift": false, "gear": 0, "frame": 408}, {"throttle": 0.45390060544013977, "steer": -0.015921231359243393, "brake": 0.0, "hand_brake": false, "reverse": false, "manual_gear_shift": false, "gear": 0, "frame": 409}, {"throttle": 0.4583287239074707, "steer": -0.0019345091423019767, "brake": 0.0, "hand_brake": false, "reverse": false, "manual_gear_shift": false, "gear": 0, "frame": 410}, {"throttle": 0.45315006375312805, "steer": 0.005449168384075165, "brake": 0.0, "hand_brake": false, "reverse": false, "manual_gear_shift": false, "gear": 0, "frame": 411}, {"throttle": 0.46171239018440247, "steer": -0.09455083310604095, "brake": 0.0, "hand_brake": false, "reverse": false, "manual_gear_shift": false, "gear": 0, "frame": 412}, {"throttle": 0.4547257423400879, "steer": -0.08269035816192627, "brake": 0.0, "hand_brake": false, "reverse": false, "manual_gear_shift": false, "gear": 0, "frame": 413}, {"throttle": 0.46064406633377075, "steer": -0.023224927484989166, "brake": 0.0, "hand_brake": false, "reverse": false, "manual_gear_shift": false, "gear": 0, "frame": 414}, {"throttle": 0.44417592883110046, "steer": 0.0048979041166603565, "brake": 0.0, "hand_brake": false, "reverse": false, "manual_gear_shift": false, "gear": 0, "frame": 415}, {"throttle": 0.4562041759490967, "steer": -0.05304596573114395, "brake": 0.0, "hand_brake": false, "reverse": false, "manual_gear_shift": false, "gear": 0, "frame": 416}, {"throttle": 0.4324668347835541, "steer": -0.09554748237133026, "brake": 0.0, "hand_brake": false, "reverse": false, "manual_gear_shift": false, "gear": 0, "frame": 417}, {"throttle": 0.4164517819881439, "steer": -0.057630233466625214, "brake": 0.0, "hand_brake": false, "reverse": false, "manual_gear_shift": false, "gear": 0, "frame": 418}, {"throttle": 0.44076284766197205, "steer": 0.012645110487937927, "brake": 0.0, "hand_brake": false, "reverse": false, "manual_gear_shift": false, "gear": 0, "frame": 419}, {"throttle": 0.43224143981933594, "steer": 0.049095991998910904, "brake": 0.0, "hand_brake": false, "reverse": false, "manual_gear_shift": false, "gear": 0, "frame": 420}, {"throttle": 0.41455215215682983, "steer": 0.023236501961946487, "brake": 0.0, "hand_brake": false, "reverse": false, "manual_gear_shift": false, "gear": 0, "frame": 421}, {"throttle": 0.40413782000541687, "steer": 0.04955422878265381, "brake": 0.0, "hand_brake": false, "reverse": false, "manual_gear_shift": false, "gear": 0, "frame": 422}, {"throttle": 0.38406363129615784, "steer": 0.07520539313554764, "brake": 0.0, "hand_brake": false, "reverse": false, "manual_gear_shift": false, "gear": 0, "frame": 423}, {"throttle": 0.37458187341690063, "steer": 0.009808188304305077, "brake": 0.0, "hand_brake": false, "reverse": false, "manual_gear_shift": false, "gear": 0, "frame": 424}, {"throttle": 0.3531832993030548, "steer": -0.010225905105471611, "brake": 0.0, "hand_brake": false, "reverse": false, "manual_gear_shift": false, "gear": 0, "frame": 425}, {"throttle": 0.34876707196235657, "steer": 0.005853748880326748, "brake": 0.0, "hand_brake": false, "reverse": false, "manual_gear_shift": false, "gear": 0, "frame": 426}, {"throttle": 0.34569019079208374, "steer": 0.05048244073987007, "brake": 0.0, "hand_brake": false, "reverse": false, "manual_gear_shift": false, "gear": 0, "frame": 427}, {"throttle": 0.34114089608192444, "steer": 0.05197960138320923, "brake": 0.0, "hand_brake": false, "reverse": false, "manual_gear_shift": false, "gear": 0, "frame": 428}, {"throttle": 0.32890966534614563, "steer": 0.01633092761039734, "brake": 0.0, "hand_brake": false, "reverse": false, "manual_gear_shift": false, "gear": 0, "frame": 429}, {"throttle": 0.31861358880996704, "steer": -0.008720374666154385, "brake": 0.0, "hand_brake": false, "reverse": false, "manual_gear_shift": false, "gear": 0, "frame": 430}, {"throttle": 0.3219447433948517, "steer": 0.016094503924250603, "brake": 0.0, "hand_brake": false, "reverse": false, "manual_gear_shift": false, "gear": 0, "frame": 431}, {"throttle": 0.3437023162841797, "steer": 0.0008439806406386197, "brake": 0.0, "hand_brake": false, "reverse": false, "manual_gear_shift": false, "gear": 0, "frame": 432}, {"throttle": 0.36775821447372437, "steer": 0.005078906659036875, "brake": 0.0, "hand_brake": false, "reverse": false, "manual_gear_shift": false, "gear": 0, "frame": 433}, {"throttle": 0.38171011209487915, "steer": 0.01523976493626833, "brake": 0.0, "hand_brake": false, "reverse": false, "manual_gear_shift": false, "gear": 0, "frame": 434}, {"throttle": 0.38175177574157715, "steer": -0.033686112612485886, "brake": 0.0, "hand_brake": false, "reverse": false, "manual_gear_shift": false, "gear": 0, "frame": 435}, {"throttle": 0.38125714659690857, "steer": -0.011029872111976147, "brake": 0.0, "hand_brake": false, "reverse": false, "manual_gear_shift": false, "gear": 0, "frame": 436}, {"throttle": 0.3934612274169922, "steer": 0.0026296081487089396, "brake": 0.0, "hand_brake": false, "reverse": false, "manual_gear_shift": false, "gear": 0, "frame": 437}, {"throttle": 0.3954114019870758, "steer": -0.0025478668976575136, "brake": 0.0, "hand_brake": false, "reverse": false, "manual_gear_shift": false, "gear": 0, "frame": 438}, {"throttle": 0.39944297075271606, "steer": -0.005455957259982824, "brake": 0.0, "hand_brake": false, "reverse": false, "manual_gear_shift": false, "gear": 0, "frame": 439}, {"throttle": 0.4110255539417267, "steer": 0.023339277133345604, "brake": 0.0, "hand_brake": false, "reverse": false, "manual_gear_shift": false, "gear": 0, "frame": 440}, {"throttle": 0.4269304871559143, "steer": -0.0225739236921072, "brake": 0.0, "hand_brake": false, "reverse": false, "manual_gear_shift": false, "gear": 0, "frame": 441}, {"throttle": 0.4289100170135498, "steer": -0.010550068691372871, "brake": 0.0, "hand_brake": false, "reverse": false, "manual_gear_shift": false, "gear": 0, "frame": 442}, {"throttle": 0.42738425731658936, "steer": -0.002041489351540804, "brake": 0.0, "hand_brake": false, "reverse": false, "manual_gear_shift": false, "gear": 0, "frame": 443}, {"throttle": 0.4350845217704773, "steer": -0.02452182024717331, "brake": 0.0, "hand_brake": false, "reverse": false, "manual_gear_shift": false, "gear": 0, "frame": 444}, {"throttle": 0.42614510655403137, "steer": -0.042903829365968704, "brake": 0.0, "hand_brake": false, "reverse": false, "manual_gear_shift": false, "gear": 0, "frame": 445}, {"throttle": 0.4106886684894562, "steer": -0.011521629989147186, "brake": 0.0, "hand_brake": false, "reverse": false, "manual_gear_shift": false, "gear": 0, "frame": 446}, {"throttle": 0.3949263393878937, "steer": -0.047198280692100525, "brake": 0.0, "hand_brake": false, "reverse": false, "manual_gear_shift": false, "gear": 0, "frame": 447}, {"throttle": 0.3750267028808594, "steer": -0.03105763904750347, "brake": 0.0, "hand_brake": false, "reverse": false, "manual_gear_shift": false, "gear": 0, "frame": 448}, {"throttle": 0.36051246523857117, "steer": 0.0003272999310865998, "brake": 0.0, "hand_brake": false, "reverse": false, "manual_gear_shift": false, "gear": 0, "frame": 449}, {"throttle": 0.35370463132858276, "steer": 0.0533268079161644, "brake": 0.0, "hand_brake": false, "reverse": false, "manual_gear_shift": false, "gear": 0, "frame": 450}, {"throttle": 0.33780336380004883, "steer": 0.07023037225008011, "brake": 0.0, "hand_brake": false, "reverse": false, "manual_gear_shift": false, "gear": 0, "frame": 451}, {"throttle": 0.3318552076816559, "steer": 0.027651704847812653, "brake": 0.0, "hand_brake": false, "reverse": false, "manual_gear_shift": false, "gear": 0, "frame": 452}, {"throttle": 0.35010528564453125, "steer": -0.008892823942005634, "brake": 0.0, "hand_brake": false, "reverse": false, "manual_gear_shift": false, "gear": 0, "frame": 453}, {"throttle": 0.36812904477119446, "steer": -0.032943449914455414, "brake": 0.0, "hand_brake": false, "reverse": false, "manual_gear_shift": false, "gear": 0, "frame": 454}, {"throttle": 0.4066651463508606, "steer": 0.006488770712167025, "brake": 0.0, "hand_brake": false, "reverse": false, "manual_gear_shift": false, "gear": 0, "frame": 455}, {"throttle": 0.41510748863220215, "steer": 0.04694698378443718, "brake": 0.0, "hand_brake": false, "reverse": false, "manual_gear_shift": false, "gear": 0, "frame": 456}, {"throttle": 0.4358493983745575, "steer": 0.008695092052221298, "brake": 0.0, "hand_brake": false, "reverse": false, "manual_gear_shift": false, "gear": 0, "frame": 457}, {"throttle": 0.452183336019516, "steer": -0.012533675879240036, "brake": 0.0, "hand_brake": false, "reverse": false, "manual_gear_shift": false, "gear": 0, "frame": 458}, {"throttle": 0.4739127457141876, "steer": 0.028176570311188698, "brake": 0.0, "hand_brake": false, "reverse": false, "manual_gear_shift": false, "gear": 0, "frame": 459}, {"throttle": 0.487209677696228, "steer": 0.029782013967633247, "brake": 0.0, "hand_brake": false, "reverse": false, "manual_gear_shift": false, "gear": 0, "frame": 460}, {"throttle": 0.478689044713974, "steer": 0.013666355982422829, "brake": 0.0, "hand_brake": false, "reverse": false, "manual_gear_shift": false, "gear": 0, "frame": 461}, {"throttle": 0.4582683742046356, "steer": 0.04176079109311104, "brake": 0.0, "hand_brake": false, "reverse": false, "manual_gear_shift": false, "gear": 0, "frame": 462}, {"throttle": 0.4530215859413147, "steer": 0.011724579147994518, "brake": 0.0, "hand_brake": false, "reverse": false, "manual_gear_shift": false, "gear": 0, "frame": 463}, {"throttle": 0.4273304343223572, "steer": -0.023247120901942253, "brake": 0.0, "hand_brake": false, "reverse": false, "manual_gear_shift": false, "gear": 0, "frame": 464}, {"throttle": 0.4046213924884796, "steer": 0.016068218275904655, "brake": 0.0, "hand_brake": false, "reverse": false, "manual_gear_shift": false, "gear": 0, "frame": 465}, {"throttle": 0.3863297700881958, "steer": 0.05438142269849777, "brake": 0.0, "hand_brake": false, "reverse": false, "manual_gear_shift": false, "gear": 0, "frame": 466}, {"throttle": 0.3864726126194, "steer": 0.031408172100782394, "brake": 0.0, "hand_brake": false, "reverse": false, "manual_gear_shift": false, "gear": 0, "frame": 467}, {"throttle": 0.3944587707519531, "steer": -0.019553057849407196, "brake": 0.0, "hand_brake": false, "reverse": false, "manual_gear_shift": false, "gear": 0, "frame": 468}, {"throttle": 0.39489850401878357, "steer": -0.10014420002698898, "brake": 0.0, "hand_brake": false, "reverse": false, "manual_gear_shift": false, "gear": 0, "frame": 469}, {"throttle": 0.38104820251464844, "steer": -0.12303187698125839, "brake": 0.0, "hand_brake": false, "reverse": false, "manual_gear_shift": false, "gear": 0, "frame": 470}, {"throttle": 0.3770436942577362, "steer": -0.06639450788497925, "brake": 0.0, "hand_brake": false, "reverse": false, "manual_gear_shift": false, "gear": 0, "frame": 471}, {"throttle": 0.36739403009414673, "steer": -0.013420413248240948, "brake": 0.0, "hand_brake": false, "reverse": false, "manual_gear_shift": false, "gear": 0, "frame": 472}, {"throttle": 0.36320725083351135, "steer": 0.005679312162101269, "brake": 0.0, "hand_brake": false, "reverse": false, "manual_gear_shift": false, "gear": 0, "frame": 473}, {"throttle": 0.36183977127075195, "steer": -0.0006711540627293289, "brake": 0.0, "hand_brake": false, "reverse": false, "manual_gear_shift": false, "gear": 0, "frame": 474}, {"throttle": 0.3728613555431366, "steer": -0.02745100110769272, "brake": 0.0, "hand_brake": false, "reverse": false, "manual_gear_shift": false, "gear": 0, "frame": 475}, {"throttle": 0.3836257755756378, "steer": -0.01796511933207512, "brake": 0.0, "hand_brake": false, "reverse": false, "manual_gear_shift": false, "gear": 0, "frame": 476}, {"throttle": 0.0, "steer": -0.024576975032687187, "brake": 0.002982456237077713, "hand_brake": false, "reverse": false, "manual_gear_shift": false, "gear": 0, "frame": 477}, {"throttle": 0.027987496927380562, "steer": -0.0277803223580122, "brake": 0.0, "hand_brake": false, "reverse": false, "manual_gear_shift": false, "gear": 0, "frame": 478}, {"throttle": 0.07226162403821945, "steer": -0.034630633890628815, "brake": 0.0, "hand_brake": false, "reverse": false, "manual_gear_shift": false, "gear": 0, "frame": 479}, {"throttle": 0.13007870316505432, "steer": -0.03262502700090408, "brake": 0.0, "hand_brake": false, "reverse": false, "manual_gear_shift": false, "gear": 0, "frame": 480}, {"throttle": 0.18577390909194946, "steer": -0.030960092321038246, "brake": 0.0, "hand_brake": false, "reverse": false, "manual_gear_shift": false, "gear": 0, "frame": 481}, {"throttle": 0.2547856569290161, "steer": -0.02002292312681675, "brake": 0.0, "hand_brake": false, "reverse": false, "manual_gear_shift": false, "gear": 0, "frame": 482}, {"throttle": 0.3147883117198944, "steer": -0.008821526542305946, "brake": 0.0, "hand_brake": false, "reverse": false, "manual_gear_shift": false, "gear": 0, "frame": 483}, {"throttle": 0.36301615834236145, "steer": -0.009319759905338287, "brake": 0.0, "hand_brake": false, "reverse": false, "manual_gear_shift": false, "gear": 0, "frame": 484}, {"throttle": 0.4086008071899414, "steer": -0.006652714218944311, "brake": 0.0, "hand_brake": false, "reverse": false, "manual_gear_shift": false, "gear": 0, "frame": 485}, {"throttle": 0.4459480345249176, "steer": 0.0012908678036183119, "brake": 0.0, "hand_brake": false, "reverse": false, "manual_gear_shift": false, "gear": 0, "frame": 486}, {"throttle": 0.4678950011730194, "steer": -0.004659623838961124, "brake": 0.0, "hand_brake": false, "reverse": false, "manual_gear_shift": false, "gear": 0, "frame": 487}, {"throttle": 0.4690643548965454, "steer": -0.014345637522637844, "brake": 0.0, "hand_brake": false, "reverse": false, "manual_gear_shift": false, "gear": 0, "frame": 488}, {"throttle": 0.465082049369812, "steer": -0.03141377493739128, "brake": 0.0, "hand_brake": false, "reverse": false, "manual_gear_shift": false, "gear": 0, "frame": 489}, {"throttle": 0.4568607211112976, "steer": -0.04302496835589409, "brake": 0.0, "hand_brake": false, "reverse": false, "manual_gear_shift": false, "gear": 0, "frame": 490}, {"throttle": 0.438955694437027, "steer": -0.03948838263750076, "brake": 0.0, "hand_brake": false, "reverse": false, "manual_gear_shift": false, "gear": 0, "frame": 491}, {"throttle": 0.4164421558380127, "steer": -0.027231942862272263, "brake": 0.0, "hand_brake": false, "reverse": false, "manual_gear_shift": false, "gear": 0, "frame": 492}, {"throttle": 0.4057518541812897, "steer": -0.026044145226478577, "brake": 0.0, "hand_brake": false, "reverse": false, "manual_gear_shift": false, "gear": 0, "frame": 493}, {"throttle": 0.41553428769111633, "steer": -0.04487974941730499, "brake": 0.0, "hand_brake": false, "reverse": false, "manual_gear_shift": false, "gear": 0, "frame": 494}, {"throttle": 0.41564247012138367, "steer": -0.06295962631702423, "brake": 0.0, "hand_brake": false, "reverse": false, "manual_gear_shift": false, "gear": 0, "frame": 495}, {"throttle": 0.4182392656803131, "steer": -0.06919760257005692, "brake": 0.0, "hand_brake": false, "reverse": false, "manual_gear_shift": false, "gear": 0, "frame": 496}, {"throttle": 0.4382171928882599, "steer": -0.06707419455051422, "brake": 0.0, "hand_brake": false, "reverse": false, "manual_gear_shift": false, "gear": 0, "frame": 497}, {"throttle": 0.4499821364879608, "steer": -0.05780765041708946, "brake": 0.0, "hand_brake": false, "reverse": false, "manual_gear_shift": false, "gear": 0, "frame": 498}, {"throttle": 0.466706782579422, "steer": -0.06483954936265945, "brake": 0.0, "hand_brake": false, "reverse": false, "manual_gear_shift": false, "gear": 0, "frame": 499}, {"throttle": 0.4734388291835785, "steer": -0.07100651413202286, "brake": 0.0, "hand_brake": false, "reverse": false, "manual_gear_shift": false, "gear": 0, "frame": 500}, {"throttle": 0.48682260513305664, "steer": -0.07804829627275467, "brake": 0.0, "hand_brake": false, "reverse": false, "manual_gear_shift": false, "gear": 0, "frame": 501}, {"throttle": 0.4794807732105255, "steer": -0.06123979389667511, "brake": 0.0, "hand_brake": false, "reverse": false, "manual_gear_shift": false, "gear": 0, "frame": 502}, {"throttle": 0.47264599800109863, "steer": -0.05115484073758125, "brake": 0.0, "hand_brake": false, "reverse": false, "manual_gear_shift": false, "gear": 0, "frame": 503}, {"throttle": 0.4540083706378937, "steer": -0.038966380059719086, "brake": 0.0, "hand_brake": false, "reverse": false, "manual_gear_shift": false, "gear": 0, "frame": 504}, {"throttle": 0.43229442834854126, "steer": -0.039665233343839645, "brake": 0.0, "hand_brake": false, "reverse": false, "manual_gear_shift": false, "gear": 0, "frame": 505}, {"throttle": 0.4235425889492035, "steer": -0.036823518574237823, "brake": 0.0, "hand_brake": false, "reverse": false, "manual_gear_shift": false, "gear": 0, "frame": 506}, {"throttle": 0.4102785587310791, "steer": -0.03284383565187454, "brake": 0.0, "hand_brake": false, "reverse": false, "manual_gear_shift": false, "gear": 0, "frame": 507}, {"throttle": 0.40477460622787476, "steer": -0.17137642204761505, "brake": 0.0, "hand_brake": false, "reverse": false, "manual_gear_shift": false, "gear": 0, "frame": 508}, {"throttle": 0.4170228838920593, "steer": -0.14456415176391602, "brake": 0.0, "hand_brake": false, "reverse": false, "manual_gear_shift": false, "gear": 0, "frame": 509}, {"throttle": 0.3973449468612671, "steer": -0.10712204873561859, "brake": 0.0, "hand_brake": false, "reverse": false, "manual_gear_shift": false, "gear": 0, "frame": 510}, {"throttle": 0.39866113662719727, "steer": -0.06504140049219131, "brake": 0.0, "hand_brake": false, "reverse": false, "manual_gear_shift": false, "gear": 0, "frame": 511}, {"throttle": 0.375688374042511, "steer": -0.023052213713526726, "brake": 0.0, "hand_brake": false, "reverse": false, "manual_gear_shift": false, "gear": 0, "frame": 512}, {"throttle": 0.3643743395805359, "steer": -0.0009463140740990639, "brake": 0.0, "hand_brake": false, "reverse": false, "manual_gear_shift": false, "gear": 0, "frame": 513}, {"throttle": 0.37032270431518555, "steer": 0.01984262838959694, "brake": 0.0, "hand_brake": false, "reverse": false, "manual_gear_shift": false, "gear": 0, "frame": 514}, {"throttle": 0.37020444869995117, "steer": 0.0436953641474247, "brake": 0.0, "hand_brake": false, "reverse": false, "manual_gear_shift": false, "gear": 0, "frame": 515}, {"throttle": 0.3747139275074005, "steer": -0.15630464255809784, "brake": 0.0, "hand_brake": false, "reverse": false, "manual_gear_shift": false, "gear": 0, "frame": 516}, {"throttle": 0.3752172589302063, "steer": -0.21359053254127502, "brake": 0.0, "hand_brake": false, "reverse": false, "manual_gear_shift": false, "gear": 0, "frame": 517}, {"throttle": 0.40112295746803284, "steer": -0.19307799637317657, "brake": 0.0, "hand_brake": false, "reverse": false, "manual_gear_shift": false, "gear": 0, "frame": 518}, {"throttle": 0.4083493947982788, "steer": -0.1583530604839325, "brake": 0.0, "hand_brake": false, "reverse": false, "manual_gear_shift": false, "gear": 0, "frame": 519}, {"throttle": 0.42837169766426086, "steer": -0.11143495887517929, "brake": 0.0, "hand_brake": false, "reverse": false, "manual_gear_shift": false, "gear": 0, "frame": 520}, {"throttle": 0.41531091928482056, "steer": -0.06851505488157272, "brake": 0.0, "hand_brake": false, "reverse": false, "manual_gear_shift": false, "gear": 0, "frame": 521}, {"throttle": 0.40038540959358215, "steer": -0.03869584575295448, "brake": 0.0, "hand_brake": false, "reverse": false, "manual_gear_shift": false, "gear": 0, "frame": 522}, {"throttle": 0.38411954045295715, "steer": -0.23869584500789642, "brake": 0.0, "hand_brake": false, "reverse": false, "manual_gear_shift": false, "gear": 0, "frame": 523}, {"throttle": 0.3877968192100525, "steer": -0.30819788575172424, "brake": 0.0, "hand_brake": false, "reverse": false, "manual_gear_shift": false, "gear": 0, "frame": 524}, {"throttle": 0.3873838484287262, "steer": -0.26615840196609497, "brake": 0.0, "hand_brake": false, "reverse": false, "manual_gear_shift": false, "gear": 0, "frame": 525}, {"throttle": 0.40691128373146057, "steer": -0.20995929837226868, "brake": 0.0, "hand_brake": false, "reverse": false, "manual_gear_shift": false, "gear": 0, "frame": 526}, {"throttle": 0.41673529148101807, "steer": -0.14231809973716736, "brake": 0.0, "hand_brake": false, "reverse": false, "manual_gear_shift": false, "gear": 0, "frame": 527}, {"throttle": 0.4024576246738434, "steer": -0.0730694904923439, "brake": 0.0, "hand_brake": false, "reverse": false, "manual_gear_shift": false, "gear": 0, "frame": 528}, {"throttle": 0.38015517592430115, "steer": -0.020883576944470406, "brake": 0.0, "hand_brake": false, "reverse": false, "manual_gear_shift": false, "gear": 0, "frame": 529}, {"throttle": 0.39370790123939514, "steer": -0.2208835780620575, "brake": 0.0, "hand_brake": false, "reverse": false, "manual_gear_shift": false, "gear": 0, "frame": 530}, {"throttle": 0.40321531891822815, "steer": -0.351313054561615, "brake": 0.0, "hand_brake": false, "reverse": false, "manual_gear_shift": false, "gear": 0, "frame": 531}, {"throttle": 0.43918564915657043, "steer": -0.3314378261566162, "brake": 0.0, "hand_brake": false, "reverse": false, "manual_gear_shift": false, "gear": 0, "frame": 532}, {"throttle": 0.44492605328559875, "steer": -0.2995820641517639, "brake": 0.0, "hand_brake": false, "reverse": false, "manual_gear_shift": false, "gear": 0, "frame": 533}, {"throttle": 0.4461461305618286, "steer": -0.2593834400177002, "brake": 0.0, "hand_brake": false, "reverse": false, "manual_gear_shift": false, "gear": 0, "frame": 534}, {"throttle": 0.4211968183517456, "steer": -0.2217080444097519, "brake": 0.0, "hand_brake": false, "reverse": false, "manual_gear_shift": false, "gear": 0, "frame": 535}, {"throttle": 0.4140104353427887, "steer": -0.42170804738998413, "brake": 0.0, "hand_brake": false, "reverse": false, "manual_gear_shift": false, "gear": 0, "frame": 536}, {"throttle": 0.4374188184738159, "steer": -0.49270766973495483, "brake": 0.0, "hand_brake": false, "reverse": false, "manual_gear_shift": false, "gear": 0, "frame": 537}, {"throttle": 0.48758959770202637, "steer": -0.42858994007110596, "brake": 0.0, "hand_brake": false, "reverse": false, "manual_gear_shift": false, "gear": 0, "frame": 538}, {"throttle": 0.49771034717559814, "steer": -0.3539397716522217, "brake": 0.0, "hand_brake": false, "reverse": false, "manual_gear_shift": false, "gear": 0, "frame": 539}, {"throttle": 0.4992296099662781, "steer": -0.2721358835697174, "brake": 0.0, "hand_brake": false, "reverse": false, "manual_gear_shift": false, "gear": 0, "frame": 540}, {"throttle": 0.4976612329483032, "steer": -0.18278081715106964, "brake": 0.0, "hand_brake": false, "reverse": false, "manual_gear_shift": false, "gear": 0, "frame": 541}, {"throttle": 0.43880710005760193, "steer": -0.09748085588216782, "brake": 0.0, "hand_brake": false, "reverse": false, "manual_gear_shift": false, "gear": 0, "frame": 542}, {"throttle": 0.3884177505970001, "steer": -0.03087848611176014, "brake": 0.0, "hand_brake": false, "reverse": false, "manual_gear_shift": false, "gear": 0, "frame": 543}, {"throttle": 0.3409907817840576, "steer": 0.01997792162001133, "brake": 0.0, "hand_brake": false, "reverse": false, "manual_gear_shift": false, "gear": 0, "frame": 544}, {"throttle": 0.31148719787597656, "steer": 0.03335624933242798, "brake": 0.0, "hand_brake": false, "reverse": false, "manual_gear_shift": false, "gear": 0, "frame": 545}, {"throttle": 0.29607877135276794, "steer": 0.031062619760632515, "brake": 0.0, "hand_brake": false, "reverse": false, "manual_gear_shift": false, "gear": 0, "frame": 546}, {"throttle": 0.28762853145599365, "steer": 0.021599948406219482, "brake": 0.0, "hand_brake": false, "reverse": false, "manual_gear_shift": false, "gear": 0, "frame": 547}, {"throttle": 0.2997407615184784, "steer": 0.02089800126850605, "brake": 0.0, "hand_brake": false, "reverse": false, "manual_gear_shift": false, "gear": 0, "frame": 548}, {"throttle": 0.3142366111278534, "steer": 0.027084384113550186, "brake": 0.0, "hand_brake": false, "reverse": false, "manual_gear_shift": false, "gear": 0, "frame": 549}, {"throttle": 0.3492676615715027, "steer": 0.04692559689283371, "brake": 0.0, "hand_brake": false, "reverse": false, "manual_gear_shift": false, "gear": 0, "frame": 550}, {"throttle": 0.38097891211509705, "steer": 0.06866855174303055, "brake": 0.0, "hand_brake": false, "reverse": false, "manual_gear_shift": false, "gear": 0, "frame": 551}, {"throttle": 0.4066704213619232, "steer": 0.08480246365070343, "brake": 0.0, "hand_brake": false, "reverse": false, "manual_gear_shift": false, "gear": 0, "frame": 552}, {"throttle": 0.42953452467918396, "steer": 0.09830357879400253, "brake": 0.0, "hand_brake": false, "reverse": false, "manual_gear_shift": false, "gear": 0, "frame": 553}, {"throttle": 0.4483834505081177, "steer": 0.10131347179412842, "brake": 0.0, "hand_brake": false, "reverse": false, "manual_gear_shift": false, "gear": 0, "frame": 554}, {"throttle": 0.44527050852775574, "steer": 0.1012536957859993, "brake": 0.0, "hand_brake": false, "reverse": false, "manual_gear_shift": false, "gear": 0, "frame": 555}, {"throttle": 0.43584343791007996, "steer": 0.10936632752418518, "brake": 0.0, "hand_brake": false, "reverse": false, "manual_gear_shift": false, "gear": 0, "frame": 556}, {"throttle": 0.42428648471832275, "steer": 0.1267046183347702, "brake": 0.0, "hand_brake": false, "reverse": false, "manual_gear_shift": false, "gear": 0, "frame": 557}, {"throttle": 0.4182877838611603, "steer": 0.15467362105846405, "brake": 0.0, "hand_brake": false, "reverse": false, "manual_gear_shift": false, "gear": 0, "frame": 558}, {"throttle": 0.0, "steer": 0.0, "brake": 1.0, "hand_brake": false, "reverse": false, "manual_gear_shift": false, "gear": 0, "frame": 559}]